Workbook

Sheet Summary
A1: 2027 Covenant Test Summary
A2: Every test was read from the loan documents.
A3: =HYPERLINK("#'2027 Calendar'!A1","Dated calendar") -> Dated calendar | B3: =HYPERLINK("#'Ongoing Obligations'!A1","Ongoing obligations") -> Ongoing obligations | C3: =HYPERLINK("#'Property Reference'!A1","Property reference") -> Property reference
A5: 2027 monthly workload
A6: Month | B6: New tests | C6: Maturities
A7: =DATE(2027,1,1) -> 46388 | B7: =COUNTIFS('2027 Calendar'!$A$5:$A$45,">="&$A7,'2027 Calendar'!$A$5:$A$45,"<"&EDATE($A7,1),'2027 Calendar'!$D$5:$D$45,"Test") -> 0 | C7: =COUNTIFS('2027 Calendar'!$A$5:$A$45,">="&$A7,'2027 Calendar'!$A$5:$A$45,"<"&EDATE($A7,1),'2027 Calendar'!$D$5:$D$45,"Maturity") -> 0
A8: =DATE(2027,2,1) -> 46419 | B8: =COUNTIFS('2027 Calendar'!$A$5:$A$45,">="&$A8,'2027 Calendar'!$A$5:$A$45,"<"&EDATE($A8,1),'2027 Calendar'!$D$5:$D$45,"Test") -> 0 | C8: =COUNTIFS('2027 Calendar'!$A$5:$A$45,">="&$A8,'2027 Calendar'!$A$5:$A$45,"<"&EDATE($A8,1),'2027 Calendar'!$D$5:$D$45,"Maturity") -> 0
A9: =DATE(2027,3,1) -> 46447 | B9: =COUNTIFS('2027 Calendar'!$A$5:$A$45,">="&$A9,'2027 Calendar'!$A$5:$A$45,"<"&EDATE($A9,1),'2027 Calendar'!$D$5:$D$45,"Test") -> 1 | C9: =COUNTIFS('2027 Calendar'!$A$5:$A$45,">="&$A9,'2027 Calendar'!$A$5:$A$45,"<"&EDATE($A9,1),'2027 Calendar'!$D$5:$D$45,"Maturity") -> 0
A10: =DATE(2027,4,1) -> 46478 | B10: =COUNTIFS('2027 Calendar'!$A$5:$A$45,">="&$A10,'2027 Calendar'!$A$5:$A$45,"<"&EDATE($A10,1),'2027 Calendar'!$D$5:$D$45,"Test") -> 2 | C10: =COUNTIFS('2027 Calendar'!$A$5:$A$45,">="&$A10,'2027 Calendar'!$A$5:$A$45,"<"&EDATE($A10,1),'2027 Calendar'!$D$5:$D$45,"Maturity") -> 0
A11: =DATE(2027,5,1) -> 46508 | B11: =COUNTIFS('2027 Calendar'!$A$5:$A$45,">="&$A11,'2027 Calendar'!$A$5:$A$45,"<"&EDATE($A11,1),'2027 Calendar'!$D$5:$D$45,"Test") -> 1 | C11: =COUNTIFS('2027 Calendar'!$A$5:$A$45,">="&$A11,'2027 Calendar'!$A$5:$A$45,"<"&EDATE($A11,1),'2027 Calendar'!$D$5:$D$45,"Maturity") -> 1
A12: =DATE(2027,6,1) -> 46539 | B12: =COUNTIFS('2027 Calendar'!$A$5:$A$45,">="&$A12,'2027 Calendar'!$A$5:$A$45,"<"&EDATE($A12,1),'2027 Calendar'!$D$5:$D$45,"Test") -> 1 | C12: =COUNTIFS('2027 Calendar'!$A$5:$A$45,">="&$A12,'2027 Calendar'!$A$5:$A$45,"<"&EDATE($A12,1),'2027 Calendar'!$D$5:$D$45,"Maturity") -> 0
A13: =DATE(2027,7,1) -> 46569 | B13: =COUNTIFS('2027 Calendar'!$A$5:$A$45,">="&$A13,'2027 Calendar'!$A$5:$A$45,"<"&EDATE($A13,1),'2027 Calendar'!$D$5:$D$45,"Test") -> 0 | C13: =COUNTIFS('2027 Calendar'!$A$5:$A$45,">="&$A13,'2027 Calendar'!$A$5:$A$45,"<"&EDATE($A13,1),'2027 Calendar'!$D$5:$D$45,"Maturity") -> 0
A14: =DATE(2027,8,1) -> 46600 | B14: =COUNTIFS('2027 Calendar'!$A$5:$A$45,">="&$A14,'2027 Calendar'!$A$5:$A$45,"<"&EDATE($A14,1),'2027 Calendar'!$D$5:$D$45,"Test") -> 1 | C14: =COUNTIFS('2027 Calendar'!$A$5:$A$45,">="&$A14,'2027 Calendar'!$A$5:$A$45,"<"&EDATE($A14,1),'2027 Calendar'!$D$5:$D$45,"Maturity") -> 0
A15: =DATE(2027,9,1) -> 46631 | B15: =COUNTIFS('2027 Calendar'!$A$5:$A$45,">="&$A15,'2027 Calendar'!$A$5:$A$45,"<"&EDATE($A15,1),'2027 Calendar'!$D$5:$D$45,"Test") -> 2 | C15: =COUNTIFS('2027 Calendar'!$A$5:$A$45,">="&$A15,'2027 Calendar'!$A$5:$A$45,"<"&EDATE($A15,1),'2027 Calendar'!$D$5:$D$45,"Maturity") -> 0
A16: =DATE(2027,10,1) -> 46661 | B16: =COUNTIFS('2027 Calendar'!$A$5:$A$45,">="&$A16,'2027 Calendar'!$A$5:$A$45,"<"&EDATE($A16,1),'2027 Calendar'!$D$5:$D$45,"Test") -> 0 | C16: =COUNTIFS('2027 Calendar'!$A$5:$A$45,">="&$A16,'2027 Calendar'!$A$5:$A$45,"<"&EDATE($A16,1),'2027 Calendar'!$D$5:$D$45,"Maturity") -> 0
A17: =DATE(2027,11,1) -> 46692 | B17: =COUNTIFS('2027 Calendar'!$A$5:$A$45,">="&$A17,'2027 Calendar'!$A$5:$A$45,"<"&EDATE($A17,1),'2027 Calendar'!$D$5:$D$45,"Test") -> 3 | C17: =COUNTIFS('2027 Calendar'!$A$5:$A$45,">="&$A17,'2027 Calendar'!$A$5:$A$45,"<"&EDATE($A17,1),'2027 Calendar'!$D$5:$D$45,"Maturity") -> 2
A18: =DATE(2027,12,1) -> 46722 | B18: =COUNTIFS('2027 Calendar'!$A$5:$A$45,">="&$A18,'2027 Calendar'!$A$5:$A$45,"<"&EDATE($A18,1),'2027 Calendar'!$D$5:$D$45,"Test") -> 4 | C18: =COUNTIFS('2027 Calendar'!$A$5:$A$45,">="&$A18,'2027 Calendar'!$A$5:$A$45,"<"&EDATE($A18,1),'2027 Calendar'!$D$5:$D$45,"Maturity") -> 2
A19: Total | B19: =SUM(B7:B18) -> 15 | C19: =SUM(C7:C18) -> 5
A21: New tests are counted once, on their first date, and exclude ongoing obligations.
A23: Property | B23: Lender | C23: Maturity | D23: First New Test | E23: New Tests
A24: =HYPERLINK("#'Property Reference'!B5",'Property Reference'!B5) -> Dove Valley | B24: ='Property Reference'!C5 -> Nationwide | C24: ='Property Reference'!D5 -> 46692 | D24: ='Property Reference'!F5 -> 46692 | E24: ='Property Reference'!G5 -> 1
A25: =HYPERLINK("#'Property Reference'!B6",'Property Reference'!B6) -> Spectrum Loop | B25: ='Property Reference'!C6 -> Nationwide | C25: ='Property Reference'!D6 -> 47014 | D25: ='Property Reference'!F6 -> None | E25: ='Property Reference'!G6 -> 0
A26: =HYPERLINK("#'Property Reference'!B7",'Property Reference'!B7) -> Fort Collins Shields | B26: ='Property Reference'!C7 -> Starwood | C26: ='Property Reference'!D7 -> 46974 | D26: ='Property Reference'!F7 -> 46608 | E26: ='Property Reference'!G7 -> 1
A27: =HYPERLINK("#'Property Reference'!B8",'Property Reference'!B8) -> Fort Collins Vine | B27: ='Property Reference'!C8 -> Western-Southern | C27: ='Property Reference'!D8 -> 47309 | D27: ='Property Reference'!F8 -> None | E27: ='Property Reference'!G8 -> 0
A28: =HYPERLINK("#'Property Reference'!B9",'Property Reference'!B9) -> Ellenton | B28: ='Property Reference'!C9 -> Kayne Anderson | C28: ='Property Reference'!D9 -> 47266 | D28: ='Property Reference'!F9 -> 46660 | E28: ='Property Reference'!G9 -> 2
A29: =HYPERLINK("#'Property Reference'!B10",'Property Reference'!B10) -> Panama City Beach | B29: ='Property Reference'!C10 -> Merchants Bank of Indiana | C29: ='Property Reference'!D10 -> 47766 | D29: ='Property Reference'!F10 -> None | E29: ='Property Reference'!G10 -> 0
A30: =HYPERLINK("#'Property Reference'!B11",'Property Reference'!B11) -> Ponte Vedra | B30: ='Property Reference'!C11 -> Trustmark | C30: ='Property Reference'!D11 -> 47162 | D30: ='Property Reference'!F11 -> None | E30: ='Property Reference'!G11 -> 0
A31: =HYPERLINK("#'Property Reference'!B12",'Property Reference'!B12) -> Port St Lucie | B31: ='Property Reference'!C12 -> Blackstone / FGL | C31: ='Property Reference'!D12 -> 46997 | D31: ='Property Reference'!F12 -> 46477 | E31: ='Property Reference'!G12 -> 1
A32: =HYPERLINK("#'Property Reference'!B13",'Property Reference'!B13) -> Sarasota | B32: ='Property Reference'!C13 -> Stifel | C32: ='Property Reference'!D13 -> 46385 | D32: ='Property Reference'!F13 -> None | E32: ='Property Reference'!G13 -> 0
A33: =HYPERLINK("#'Property Reference'!B14",'Property Reference'!B14) -> St. Augustine | B33: ='Property Reference'!C14 -> Simmons | C33: ='Property Reference'!D14 -> 46748 | D33: ='Property Reference'!F14 -> 46748 | E33: ='Property Reference'!G14 -> 1
A34: =HYPERLINK("#'Property Reference'!B15",'Property Reference'!B15) -> Venice | B34: ='Property Reference'!C15 -> UMB | C34: ='Property Reference'!D15 -> 46519 | D34: ='Property Reference'!F15 -> 46507 | E34: ='Property Reference'!G15 -> 1
A35: =HYPERLINK("#'Property Reference'!B16",'Property Reference'!B16) -> Pooler | B35: ='Property Reference'!C16 -> Fifth Third | C35: ='Property Reference'!D16 -> 46714 | D35: ='Property Reference'!F16 -> 46530 | E35: ='Property Reference'!G16 -> 2
A36: =HYPERLINK("#'Property Reference'!B17",'Property Reference'!B17) -> Stockbridge | B36: ='Property Reference'!C17 -> UMB | C36: ='Property Reference'!D17 -> 46748 | D36: ='Property Reference'!F17 -> 46565 | E36: ='Property Reference'!G17 -> 4
A37: =HYPERLINK("#'Property Reference'!B18",'Property Reference'!B18) -> Nampa Sundance | B37: ='Property Reference'!C18 -> Wintrust | C37: ='Property Reference'!D18 -> 46846 | D37: ='Property Reference'!F18 -> 46507 | E37: ='Property Reference'!G18 -> 1
A38: =HYPERLINK("#'Property Reference'!B19",'Property Reference'!B19) -> 2022 Fund (Barings) | B38: ='Property Reference'!C19 -> Barings (2022 Fund) | C38: ='Property Reference'!D19 -> 46914 | D38: ='Property Reference'!F19 -> None | E38: ='Property Reference'!G19 -> 0
A39: =HYPERLINK("#'Property Reference'!B20",'Property Reference'!B20) -> 2023 Fund (Barings) | B39: ='Property Reference'!C20 -> Barings (2023 Fund) | C39: ='Property Reference'!D20 -> 47401 | D39: ='Property Reference'!F20 -> None | E39: ='Property Reference'!G20 -> 0
A40: =HYPERLINK("#'Property Reference'!B21",'Property Reference'!B21) -> Fayetteville Van Asche | B40: ='Property Reference'!C21 -> Associated / Trustmark | C40: ='Property Reference'!D21 -> 47280 | D40: ='Property Reference'!F21 -> None | E40: ='Property Reference'!G21 -> 0
A41: =HYPERLINK("#'Property Reference'!B22",'Property Reference'!B22) -> Gilbert Val Vista | B41: ='Property Reference'!C22 -> Nationwide | C41: ='Property Reference'!D22 -> 47233 | D41: ='Property Reference'!F22 -> None | E41: ='Property Reference'!G22 -> 0
A42: =HYPERLINK("#'Property Reference'!B23",'Property Reference'!B23) -> Venetucci | B42: ='Property Reference'!C23 -> PNC | C42: ='Property Reference'!D23 -> 47245 | D42: ='Property Reference'!F23 -> None | E42: ='Property Reference'!G23 -> 0
A43: =HYPERLINK("#'Property Reference'!B24",'Property Reference'!B24) -> Longmont Hover | B43: ='Property Reference'!C24 -> Stifel | C43: ='Property Reference'!D24 -> 46923 | D43: ='Property Reference'!F24 -> 46752 | E43: ='Property Reference'!G24 -> 1
A44: =HYPERLINK("#'Property Reference'!B25",'Property Reference'!B25) -> Monument Higby | B44: ='Property Reference'!C25 -> UMB | C44: ='Property Reference'!D25 -> 47250 | D44: ='Property Reference'!F25 -> None | E44: ='Property Reference'!G25 -> 0
A45: =HYPERLINK("#'Property Reference'!B26",'Property Reference'!B26) -> Wheat Ridge | B45: ='Property Reference'!C26 -> BOKF / RCB Bank | C45: ='Property Reference'!D26 -> 46978 | D45: ='Property Reference'!F26 -> None | E45: ='Property Reference'!G26 -> 0
A46: =HYPERLINK("#'Property Reference'!B27",'Property Reference'!B27) -> Buford | B46: ='Property Reference'!C27 -> BOKF | C46: ='Property Reference'!D27 -> 47202 | D46: ='Property Reference'!F27 -> None | E46: ='Property Reference'!G27 -> 0
A47: =HYPERLINK("#'Property Reference'!B28",'Property Reference'!B28) -> Dacula | B47: ='Property Reference'!C28 -> PNC | C47: ='Property Reference'!D28 -> 47349 | D47: ='Property Reference'!F28 -> None | E47: ='Property Reference'!G28 -> 0
A48: =HYPERLINK("#'Property Reference'!B29",'Property Reference'!B29) -> Newnan | B48: ='Property Reference'!C29 -> Comerica | C48: ='Property Reference'!D29 -> June 2029 | D48: ='Property Reference'!F29 -> None | E48: ='Property Reference'!G29 -> 0
A49: =HYPERLINK("#'Property Reference'!B30",'Property Reference'!B30) -> Fishers Union | B49: ='Property Reference'!C30 -> First Internet Bank | C49: ='Property Reference'!D30 -> 47087 | D49: ='Property Reference'!F30 -> None | E49: ='Property Reference'!G30 -> 0
A50: =HYPERLINK("#'Property Reference'!B31",'Property Reference'!B31) -> Westfield 191st | B50: ='Property Reference'!C31 -> Fifth Third | C50: ='Property Reference'!D31 -> 47434 | D50: ='Property Reference'!F31 -> None | E50: ='Property Reference'!G31 -> 0
A51: =HYPERLINK("#'Property Reference'!B32",'Property Reference'!B32) -> Overland Park | B51: ='Property Reference'!C32 -> Simmons | C51: ='Property Reference'!D32 -> 47269 | D51: ='Property Reference'!F32 -> None | E51: ='Property Reference'!G32 -> 0

Sheet 2027 Calendar
A1: 2027 Test Calendar
A2: First test dates and maturities in 2027. Tests that started earlier and later recurring dates are in Covenant Tests.
A3: =HYPERLINK("#'Summary'!A1","Back to Summary") -> Back to Summary | E3: =HYPERLINK("#'Ongoing Obligations'!A1","Open ongoing obligations") -> Open ongoing obligations
A4: Date | B4: Property | C4: Lender | D4: Type | E4: Test | F4: Threshold | G4: Occurrence | H4: Reference | I4: Covenant ID
A5: 46477 | B5: =IFERROR(IF(INDEX('Covenant Tests'!$A$2:$A$107,MATCH($I5,'Covenant Tests'!$J$2:$J$107,0))="","",INDEX('Covenant Tests'!$A$2:$A$107,MATCH($I5,'Covenant Tests'!$J$2:$J$107,0))),"Source record missing") -> Port St Lucie | C5: =IFERROR(IF(INDEX('Covenant Tests'!$B$2:$B$107,MATCH($I5,'Covenant Tests'!$J$2:$J$107,0))="","",INDEX('Covenant Tests'!$B$2:$B$107,MATCH($I5,'Covenant Tests'!$J$2:$J$107,0))),"Source record missing") -> Blackstone / FGL | D5: Test | E5: Cash trap: Debt Yield and DSCR | F5: 8.00% and 1.25x | G5: First test, then quarterly | H5: =IFERROR(IF(INDEX('Covenant Tests'!$I$2:$I$107,MATCH($I5,'Covenant Tests'!$J$2:$J$107,0))="","",INDEX('Covenant Tests'!$I$2:$I$107,MATCH($I5,'Covenant Tests'!$J$2:$J$107,0))),"Source record missing") -> Loan Agreement 1.1, Cash Trap Event | I5: CT023
A6: =INDEX('Covenant Tests'!$F$2:$F$107,MATCH($I6,'Covenant Tests'!$J$2:$J$107,0)) -> 46507 | B6: =IFERROR(IF(INDEX('Covenant Tests'!$A$2:$A$107,MATCH($I6,'Covenant Tests'!$J$2:$J$107,0))="","",INDEX('Covenant Tests'!$A$2:$A$107,MATCH($I6,'Covenant Tests'!$J$2:$J$107,0))),"Source record missing") -> Venice | C6: =IFERROR(IF(INDEX('Covenant Tests'!$B$2:$B$107,MATCH($I6,'Covenant Tests'!$J$2:$J$107,0))="","",INDEX('Covenant Tests'!$B$2:$B$107,MATCH($I6,'Covenant Tests'!$J$2:$J$107,0))),"Source record missing") -> UMB | D6: Test | E6: Extension: DSCR | F6: =IFERROR(IF(INDEX('Covenant Tests'!$D$2:$D$107,MATCH($I6,'Covenant Tests'!$J$2:$J$107,0))="","",INDEX('Covenant Tests'!$D$2:$D$107,MATCH($I6,'Covenant Tests'!$J$2:$J$107,0))),"Source record missing") -> 1.10x | G6: Once | H6: =IFERROR(IF(INDEX('Covenant Tests'!$I$2:$I$107,MATCH($I6,'Covenant Tests'!$J$2:$J$107,0))="","",INDEX('Covenant Tests'!$I$2:$I$107,MATCH($I6,'Covenant Tests'!$J$2:$J$107,0))),"Source record missing") -> Note, Section 1 | I6: CT038
A7: =INDEX('Covenant Tests'!$F$2:$F$107,MATCH($I7,'Covenant Tests'!$J$2:$J$107,0)) -> 46507 | B7: =IFERROR(IF(INDEX('Covenant Tests'!$A$2:$A$107,MATCH($I7,'Covenant Tests'!$J$2:$J$107,0))="","",INDEX('Covenant Tests'!$A$2:$A$107,MATCH($I7,'Covenant Tests'!$J$2:$J$107,0))),"Source record missing") -> Nampa Sundance | C7: =IFERROR(IF(INDEX('Covenant Tests'!$B$2:$B$107,MATCH($I7,'Covenant Tests'!$J$2:$J$107,0))="","",INDEX('Covenant Tests'!$B$2:$B$107,MATCH($I7,'Covenant Tests'!$J$2:$J$107,0))),"Source record missing") -> Wintrust | D7: Test | E7: DSCR covenant, step one | F7: =IFERROR(IF(INDEX('Covenant Tests'!$D$2:$D$107,MATCH($I7,'Covenant Tests'!$J$2:$J$107,0))="","",INDEX('Covenant Tests'!$D$2:$D$107,MATCH($I7,'Covenant Tests'!$J$2:$J$107,0))),"Source record missing") -> 1.00x | G7: Once | H7: =IFERROR(IF(INDEX('Covenant Tests'!$I$2:$I$107,MATCH($I7,'Covenant Tests'!$J$2:$J$107,0))="","",INDEX('Covenant Tests'!$I$2:$I$107,MATCH($I7,'Covenant Tests'!$J$2:$J$107,0))),"Source record missing") -> Loan Agreement 9.3 | I7: CT051
A8: =INDEX('Loan Terms'!$D$2:$D$29,MATCH($B8,'Loan Terms'!$A$2:$A$29,0)) -> 46519 | B8: Venice | C8: =INDEX('Loan Terms'!$B$2:$B$29,MATCH($B8,'Loan Terms'!$A$2:$A$29,0)) -> UMB | D8: Maturity | E8: Initial maturity | H8: Note, Section 1 | I8: Maturity
A9: 46530 | B9: =IFERROR(IF(INDEX('Covenant Tests'!$A$2:$A$107,MATCH($I9,'Covenant Tests'!$J$2:$J$107,0))="","",INDEX('Covenant Tests'!$A$2:$A$107,MATCH($I9,'Covenant Tests'!$J$2:$J$107,0))),"Source record missing") -> Pooler | C9: =IFERROR(IF(INDEX('Covenant Tests'!$B$2:$B$107,MATCH($I9,'Covenant Tests'!$J$2:$J$107,0))="","",INDEX('Covenant Tests'!$B$2:$B$107,MATCH($I9,'Covenant Tests'!$J$2:$J$107,0))),"Source record missing") -> Fifth Third | D9: Test | E9: DSCR covenant, step one | F9: =IFERROR(IF(INDEX('Covenant Tests'!$D$2:$D$107,MATCH($I9,'Covenant Tests'!$J$2:$J$107,0))="","",INDEX('Covenant Tests'!$D$2:$D$107,MATCH($I9,'Covenant Tests'!$J$2:$J$107,0))),"Source record missing") -> 1.00x, at rents no lower than the Proforma Rents | G9: Standing covenant from 5/23/2027 until step two | H9: =IFERROR(IF(INDEX('Covenant Tests'!$I$2:$I$107,MATCH($I9,'Covenant Tests'!$J$2:$J$107,0))="","",INDEX('Covenant Tests'!$I$2:$I$107,MATCH($I9,'Covenant Tests'!$J$2:$J$107,0))),"Source record missing") -> Loan Agreement 9.8 | I9: CT042
A10: 46565 | B10: =IFERROR(IF(INDEX('Covenant Tests'!$A$2:$A$107,MATCH($I10,'Covenant Tests'!$J$2:$J$107,0))="","",INDEX('Covenant Tests'!$A$2:$A$107,MATCH($I10,'Covenant Tests'!$J$2:$J$107,0))),"Source record missing") -> Stockbridge | C10: =IFERROR(IF(INDEX('Covenant Tests'!$B$2:$B$107,MATCH($I10,'Covenant Tests'!$J$2:$J$107,0))="","",INDEX('Covenant Tests'!$B$2:$B$107,MATCH($I10,'Covenant Tests'!$J$2:$J$107,0))),"Source record missing") -> UMB | D10: Test | E10: Occupancy, step one | F10: 50% occupancy | G10: Standing covenant from 6/27/2027 | H10: =IFERROR(IF(INDEX('Covenant Tests'!$I$2:$I$107,MATCH($I10,'Covenant Tests'!$J$2:$J$107,0))="","",INDEX('Covenant Tests'!$I$2:$I$107,MATCH($I10,'Covenant Tests'!$J$2:$J$107,0))),"Source record missing") -> Loan Agreement 7.25 | I10: CT047
A11: 46608 | B11: =IFERROR(IF(INDEX('Covenant Tests'!$A$2:$A$107,MATCH($I11,'Covenant Tests'!$J$2:$J$107,0))="","",INDEX('Covenant Tests'!$A$2:$A$107,MATCH($I11,'Covenant Tests'!$J$2:$J$107,0))),"Source record missing") -> Fort Collins Shields | C11: =IFERROR(IF(INDEX('Covenant Tests'!$B$2:$B$107,MATCH($I11,'Covenant Tests'!$J$2:$J$107,0))="","",INDEX('Covenant Tests'!$B$2:$B$107,MATCH($I11,'Covenant Tests'!$J$2:$J$107,0))),"Source record missing") -> Starwood | D11: Test | E11: Cash trap: Debt Yield | F11: =IFERROR(IF(INDEX('Covenant Tests'!$D$2:$D$107,MATCH($I11,'Covenant Tests'!$J$2:$J$107,0))="","",INDEX('Covenant Tests'!$D$2:$D$107,MATCH($I11,'Covenant Tests'!$J$2:$J$107,0))),"Source record missing") -> 6.50% (6.75% for two straight quarters to release) | G11: Any time from the August 2027 payment date; tested off the quarterly Debt Yield calculations | H11: =IFERROR(IF(INDEX('Covenant Tests'!$I$2:$I$107,MATCH($I11,'Covenant Tests'!$J$2:$J$107,0))="","",INDEX('Covenant Tests'!$I$2:$I$107,MATCH($I11,'Covenant Tests'!$J$2:$J$107,0))),"Source record missing") -> Loan Agreement 1.1, Cash Management Event | I11: CT009
A12: 46660 | B12: =IFERROR(IF(INDEX('Covenant Tests'!$A$2:$A$107,MATCH($I12,'Covenant Tests'!$J$2:$J$107,0))="","",INDEX('Covenant Tests'!$A$2:$A$107,MATCH($I12,'Covenant Tests'!$J$2:$J$107,0))),"Source record missing") -> Ellenton | C12: =IFERROR(IF(INDEX('Covenant Tests'!$B$2:$B$107,MATCH($I12,'Covenant Tests'!$J$2:$J$107,0))="","",INDEX('Covenant Tests'!$B$2:$B$107,MATCH($I12,'Covenant Tests'!$J$2:$J$107,0))),"Source record missing") -> Kayne Anderson | D12: Test | E12: Debt Yield | F12: =IFERROR(IF(INDEX('Covenant Tests'!$D$2:$D$107,MATCH($I12,'Covenant Tests'!$J$2:$J$107,0))="","",INDEX('Covenant Tests'!$D$2:$D$107,MATCH($I12,'Covenant Tests'!$J$2:$J$107,0))),"Source record missing") -> 6.00% (7.00% to release) | G12: First test, then quarterly | H12: =IFERROR(IF(INDEX('Covenant Tests'!$I$2:$I$107,MATCH($I12,'Covenant Tests'!$J$2:$J$107,0))="","",INDEX('Covenant Tests'!$I$2:$I$107,MATCH($I12,'Covenant Tests'!$J$2:$J$107,0))),"Source record missing") -> Loan Agreement 2.5(a) | I12: CT014
A13: 46660 | B13: =IFERROR(IF(INDEX('Covenant Tests'!$A$2:$A$107,MATCH($I13,'Covenant Tests'!$J$2:$J$107,0))="","",INDEX('Covenant Tests'!$A$2:$A$107,MATCH($I13,'Covenant Tests'!$J$2:$J$107,0))),"Source record missing") -> Ellenton | C13: =IFERROR(IF(INDEX('Covenant Tests'!$B$2:$B$107,MATCH($I13,'Covenant Tests'!$J$2:$J$107,0))="","",INDEX('Covenant Tests'!$B$2:$B$107,MATCH($I13,'Covenant Tests'!$J$2:$J$107,0))),"Source record missing") -> Kayne Anderson | D13: Test | E13: Implied DSCR | F13: =IFERROR(IF(INDEX('Covenant Tests'!$D$2:$D$107,MATCH($I13,'Covenant Tests'!$J$2:$J$107,0))="","",INDEX('Covenant Tests'!$D$2:$D$107,MATCH($I13,'Covenant Tests'!$J$2:$J$107,0))),"Source record missing") -> 1.00x (1.05x to release) | G13: First test, then quarterly | H13: =IFERROR(IF(INDEX('Covenant Tests'!$I$2:$I$107,MATCH($I13,'Covenant Tests'!$J$2:$J$107,0))="","",INDEX('Covenant Tests'!$I$2:$I$107,MATCH($I13,'Covenant Tests'!$J$2:$J$107,0))),"Source record missing") -> Loan Agreement 2.5(b) | I13: CT015
A14: =INDEX('Covenant Tests'!$F$2:$F$107,MATCH($I14,'Covenant Tests'!$J$2:$J$107,0)) -> 46692 | B14: =IFERROR(IF(INDEX('Covenant Tests'!$A$2:$A$107,MATCH($I14,'Covenant Tests'!$J$2:$J$107,0))="","",INDEX('Covenant Tests'!$A$2:$A$107,MATCH($I14,'Covenant Tests'!$J$2:$J$107,0))),"Source record missing") -> Dove Valley | C14: =IFERROR(IF(INDEX('Covenant Tests'!$B$2:$B$107,MATCH($I14,'Covenant Tests'!$J$2:$J$107,0))="","",INDEX('Covenant Tests'!$B$2:$B$107,MATCH($I14,'Covenant Tests'!$J$2:$J$107,0))),"Source record missing") -> Nationwide | D14: Test | E14: Extension: Net Cash Flow coverage | F14: =IFERROR(IF(INDEX('Covenant Tests'!$D$2:$D$107,MATCH($I14,'Covenant Tests'!$J$2:$J$107,0))="","",INDEX('Covenant Tests'!$D$2:$D$107,MATCH($I14,'Covenant Tests'!$J$2:$J$107,0))),"Source record missing") -> 105% of interest at the 8.50% Base Rate | G14: Once | H14: =IFERROR(IF(INDEX('Covenant Tests'!$I$2:$I$107,MATCH($I14,'Covenant Tests'!$J$2:$J$107,0))="","",INDEX('Covenant Tests'!$I$2:$I$107,MATCH($I14,'Covenant Tests'!$J$2:$J$107,0))),"Source record missing") -> Loan Agreement 3.7(g) | I14: CT001
A15: =INDEX('Loan Terms'!$D$2:$D$29,MATCH($B15,'Loan Terms'!$A$2:$A$29,0)) -> 46692 | B15: Dove Valley | C15: =INDEX('Loan Terms'!$B$2:$B$29,MATCH($B15,'Loan Terms'!$A$2:$A$29,0)) -> Nationwide | D15: Maturity | E15: Initial maturity | H15: Loan Agreement, Initial Maturity Date | I15: Maturity
A16: 46714 | B16: =IFERROR(IF(INDEX('Covenant Tests'!$A$2:$A$107,MATCH($I16,'Covenant Tests'!$J$2:$J$107,0))="","",INDEX('Covenant Tests'!$A$2:$A$107,MATCH($I16,'Covenant Tests'!$J$2:$J$107,0))),"Source record missing") -> Pooler | C16: =IFERROR(IF(INDEX('Covenant Tests'!$B$2:$B$107,MATCH($I16,'Covenant Tests'!$J$2:$J$107,0))="","",INDEX('Covenant Tests'!$B$2:$B$107,MATCH($I16,'Covenant Tests'!$J$2:$J$107,0))),"Source record missing") -> Fifth Third | D16: Test | E16: DSCR: extension test and covenant step two | F16: =IFERROR(IF(INDEX('Covenant Tests'!$D$2:$D$107,MATCH($I16,'Covenant Tests'!$J$2:$J$107,0))="","",INDEX('Covenant Tests'!$D$2:$D$107,MATCH($I16,'Covenant Tests'!$J$2:$J$107,0))),"Source record missing") -> 1.20x | G16: Extension tested once; covenant from 11/23/2027 at the latest, then each 6/30 and 12/31 | H16: Note, Section 8; Loan Agreement 9.8 | I16: CT044
A17: =INDEX('Loan Terms'!$D$2:$D$29,MATCH($B17,'Loan Terms'!$A$2:$A$29,0)) -> 46714 | B17: Pooler | C17: =INDEX('Loan Terms'!$B$2:$B$29,MATCH($B17,'Loan Terms'!$A$2:$A$29,0)) -> Fifth Third | D17: Maturity | E17: Initial maturity | H17: Note, Section 8 | I17: Maturity
A18: =INDEX('Covenant Tests'!$F$2:$F$107,MATCH($I18,'Covenant Tests'!$J$2:$J$107,0)) -> 46721 | B18: =IFERROR(IF(INDEX('Covenant Tests'!$A$2:$A$107,MATCH($I18,'Covenant Tests'!$J$2:$J$107,0))="","",INDEX('Covenant Tests'!$A$2:$A$107,MATCH($I18,'Covenant Tests'!$J$2:$J$107,0))),"Source record missing") -> Stockbridge | C18: =IFERROR(IF(INDEX('Covenant Tests'!$B$2:$B$107,MATCH($I18,'Covenant Tests'!$J$2:$J$107,0))="","",INDEX('Covenant Tests'!$B$2:$B$107,MATCH($I18,'Covenant Tests'!$J$2:$J$107,0))),"Source record missing") -> UMB | D18: Test | E18: Extension: DSCR | F18: =IFERROR(IF(INDEX('Covenant Tests'!$D$2:$D$107,MATCH($I18,'Covenant Tests'!$J$2:$J$107,0))="","",INDEX('Covenant Tests'!$D$2:$D$107,MATCH($I18,'Covenant Tests'!$J$2:$J$107,0))),"Source record missing") -> 1.15x | G18: Once | H18: =IFERROR(IF(INDEX('Covenant Tests'!$I$2:$I$107,MATCH($I18,'Covenant Tests'!$J$2:$J$107,0))="","",INDEX('Covenant Tests'!$I$2:$I$107,MATCH($I18,'Covenant Tests'!$J$2:$J$107,0))),"Source record missing") -> Note, Section 2 | I18: CT048
A19: =INDEX('Covenant Tests'!$F$2:$F$107,MATCH($I19,'Covenant Tests'!$J$2:$J$107,0)) -> 46748 | B19: =IFERROR(IF(INDEX('Covenant Tests'!$A$2:$A$107,MATCH($I19,'Covenant Tests'!$J$2:$J$107,0))="","",INDEX('Covenant Tests'!$A$2:$A$107,MATCH($I19,'Covenant Tests'!$J$2:$J$107,0))),"Source record missing") -> St. Augustine | C19: =IFERROR(IF(INDEX('Covenant Tests'!$B$2:$B$107,MATCH($I19,'Covenant Tests'!$J$2:$J$107,0))="","",INDEX('Covenant Tests'!$B$2:$B$107,MATCH($I19,'Covenant Tests'!$J$2:$J$107,0))),"Source record missing") -> Simmons | D19: Test | E19: Extension: DSCR | F19: =IFERROR(IF(INDEX('Covenant Tests'!$D$2:$D$107,MATCH($I19,'Covenant Tests'!$J$2:$J$107,0))="","",INDEX('Covenant Tests'!$D$2:$D$107,MATCH($I19,'Covenant Tests'!$J$2:$J$107,0))),"Source record missing") -> 1.25x | G19: Once | H19: =IFERROR(IF(INDEX('Covenant Tests'!$I$2:$I$107,MATCH($I19,'Covenant Tests'!$J$2:$J$107,0))="","",INDEX('Covenant Tests'!$I$2:$I$107,MATCH($I19,'Covenant Tests'!$J$2:$J$107,0))),"Source record missing") -> Note, Extension | I19: CT034
A20: =INDEX('Loan Terms'!$D$2:$D$29,MATCH($B20,'Loan Terms'!$A$2:$A$29,0)) -> 46748 | B20: St. Augustine | C20: =INDEX('Loan Terms'!$B$2:$B$29,MATCH($B20,'Loan Terms'!$A$2:$A$29,0)) -> Simmons | D20: Maturity | E20: Initial maturity | H20: Loan Agreement, Maturity Date | I20: Maturity
A21: 46748 | B21: =IFERROR(IF(INDEX('Covenant Tests'!$A$2:$A$107,MATCH($I21,'Covenant Tests'!$J$2:$J$107,0))="","",INDEX('Covenant Tests'!$A$2:$A$107,MATCH($I21,'Covenant Tests'!$J$2:$J$107,0))),"Source record missing") -> Stockbridge | C21: =IFERROR(IF(INDEX('Covenant Tests'!$B$2:$B$107,MATCH($I21,'Covenant Tests'!$J$2:$J$107,0))="","",INDEX('Covenant Tests'!$B$2:$B$107,MATCH($I21,'Covenant Tests'!$J$2:$J$107,0))),"Source record missing") -> UMB | D21: Test | E21: Occupancy, step two | F21: 80% occupancy | G21: Standing covenant from 12/27/2027 | H21: =IFERROR(IF(INDEX('Covenant Tests'!$I$2:$I$107,MATCH($I21,'Covenant Tests'!$J$2:$J$107,0))="","",INDEX('Covenant Tests'!$I$2:$I$107,MATCH($I21,'Covenant Tests'!$J$2:$J$107,0))),"Source record missing") -> Loan Agreement 7.25 | I21: CT047
A22: 46748 | B22: =IFERROR(IF(INDEX('Covenant Tests'!$A$2:$A$107,MATCH($I22,'Covenant Tests'!$J$2:$J$107,0))="","",INDEX('Covenant Tests'!$A$2:$A$107,MATCH($I22,'Covenant Tests'!$J$2:$J$107,0))),"Source record missing") -> Stockbridge | C22: =IFERROR(IF(INDEX('Covenant Tests'!$B$2:$B$107,MATCH($I22,'Covenant Tests'!$J$2:$J$107,0))="","",INDEX('Covenant Tests'!$B$2:$B$107,MATCH($I22,'Covenant Tests'!$J$2:$J$107,0))),"Source record missing") -> UMB | D22: Test | E22: DSCR covenant | F22: =IFERROR(IF(INDEX('Covenant Tests'!$D$2:$D$107,MATCH($I22,'Covenant Tests'!$J$2:$J$107,0))="","",INDEX('Covenant Tests'!$D$2:$D$107,MATCH($I22,'Covenant Tests'!$J$2:$J$107,0))),"Source record missing") -> 1.15x | G22: 12/27/2027, then each 6/30 and 12/31 | H22: =IFERROR(IF(INDEX('Covenant Tests'!$I$2:$I$107,MATCH($I22,'Covenant Tests'!$J$2:$J$107,0))="","",INDEX('Covenant Tests'!$I$2:$I$107,MATCH($I22,'Covenant Tests'!$J$2:$J$107,0))),"Source record missing") -> Loan Agreement 7.20 | I22: CT049
A23: =INDEX('Loan Terms'!$D$2:$D$29,MATCH($B23,'Loan Terms'!$A$2:$A$29,0)) -> 46748 | B23: Stockbridge | C23: =INDEX('Loan Terms'!$B$2:$B$29,MATCH($B23,'Loan Terms'!$A$2:$A$29,0)) -> UMB | D23: Maturity | E23: Initial maturity | H23: Note, Section 2 | I23: Maturity
A24: =INDEX('Covenant Tests'!$F$2:$F$107,MATCH($I24,'Covenant Tests'!$J$2:$J$107,0)) -> 46752 | B24: =IFERROR(IF(INDEX('Covenant Tests'!$A$2:$A$107,MATCH($I24,'Covenant Tests'!$J$2:$J$107,0))="","",INDEX('Covenant Tests'!$A$2:$A$107,MATCH($I24,'Covenant Tests'!$J$2:$J$107,0))),"Source record missing") -> Longmont Hover | C24: =IFERROR(IF(INDEX('Covenant Tests'!$B$2:$B$107,MATCH($I24,'Covenant Tests'!$J$2:$J$107,0))="","",INDEX('Covenant Tests'!$B$2:$B$107,MATCH($I24,'Covenant Tests'!$J$2:$J$107,0))),"Source record missing") -> Stifel | D24: Test | E24: DSCR covenant | F24: =IFERROR(IF(INDEX('Covenant Tests'!$D$2:$D$107,MATCH($I24,'Covenant Tests'!$J$2:$J$107,0))="","",INDEX('Covenant Tests'!$D$2:$D$107,MATCH($I24,'Covenant Tests'!$J$2:$J$107,0))),"Source record missing") -> 1.10x | G24: Once | H24: =IFERROR(IF(INDEX('Covenant Tests'!$I$2:$I$107,MATCH($I24,'Covenant Tests'!$J$2:$J$107,0))="","",INDEX('Covenant Tests'!$I$2:$I$107,MATCH($I24,'Covenant Tests'!$J$2:$J$107,0))),"Source record missing") -> Loan Agreement Article 11, Debt Service Coverage Ratio | I24: CT077

Sheet Ongoing Obligations
A1: 2027 Ongoing Obligations
A2: Ongoing and event-driven requirements in effect during 2027. Expand grouped columns for lender and source reference.
A3: =HYPERLINK("#'Summary'!A1","Back to Summary") -> Back to Summary
A4: Property | B4: Lender | C4: Timing Type | D4: Test | E4: Threshold | F4: Timing / Frequency | G4: Reference | H4: Covenant ID
A5: =IFERROR(IF(INDEX('Covenant Tests'!$A$2:$A$107,MATCH($H5,'Covenant Tests'!$J$2:$J$107,0))="","",INDEX('Covenant Tests'!$A$2:$A$107,MATCH($H5,'Covenant Tests'!$J$2:$J$107,0))),"Source record missing") -> Dove Valley | B5: =IFERROR(IF(INDEX('Covenant Tests'!$B$2:$B$107,MATCH($H5,'Covenant Tests'!$J$2:$J$107,0))="","",INDEX('Covenant Tests'!$B$2:$B$107,MATCH($H5,'Covenant Tests'!$J$2:$J$107,0))),"Source record missing") -> Nationwide | C5: =IFERROR(IF(INDEX('Covenant Tests'!$E$2:$E$107,MATCH($H5,'Covenant Tests'!$J$2:$J$107,0))="","",INDEX('Covenant Tests'!$E$2:$E$107,MATCH($H5,'Covenant Tests'!$J$2:$J$107,0))),"Source record missing") -> Ongoing | D5: =HYPERLINK("#'Covenant Tests'!A"&(MATCH($H5,'Covenant Tests'!$J$2:$J$107,0)+1),INDEX('Covenant Tests'!$C$2:$C$107,MATCH($H5,'Covenant Tests'!$J$2:$J$107,0))) -> Cash sweep and distribution block | E5: =IFERROR(IF(INDEX('Covenant Tests'!$D$2:$D$107,MATCH($H5,'Covenant Tests'!$J$2:$J$107,0))="","",INDEX('Covenant Tests'!$D$2:$D$107,MATCH($H5,'Covenant Tests'!$J$2:$J$107,0))),"Source record missing") -> Until final completion, DSCR 1.00x on trailing 3 months and capitalized interest repaid | F5: =IFERROR(IF(INDEX('Covenant Tests'!$G$2:$G$107,MATCH($H5,'Covenant Tests'!$J$2:$J$107,0))="","",INDEX('Covenant Tests'!$G$2:$G$107,MATCH($H5,'Covenant Tests'!$J$2:$J$107,0))),"Source record missing") -> Ongoing; monthly | G5: =IFERROR(IF(INDEX('Covenant Tests'!$I$2:$I$107,MATCH($H5,'Covenant Tests'!$J$2:$J$107,0))="","",INDEX('Covenant Tests'!$I$2:$I$107,MATCH($H5,'Covenant Tests'!$J$2:$J$107,0))),"Source record missing") -> Loan Agreement 3.5, 7.14 | H5: CT003
A6: =IFERROR(IF(INDEX('Covenant Tests'!$A$2:$A$107,MATCH($H6,'Covenant Tests'!$J$2:$J$107,0))="","",INDEX('Covenant Tests'!$A$2:$A$107,MATCH($H6,'Covenant Tests'!$J$2:$J$107,0))),"Source record missing") -> Dove Valley | B6: =IFERROR(IF(INDEX('Covenant Tests'!$B$2:$B$107,MATCH($H6,'Covenant Tests'!$J$2:$J$107,0))="","",INDEX('Covenant Tests'!$B$2:$B$107,MATCH($H6,'Covenant Tests'!$J$2:$J$107,0))),"Source record missing") -> Nationwide | C6: =IFERROR(IF(INDEX('Covenant Tests'!$E$2:$E$107,MATCH($H6,'Covenant Tests'!$J$2:$J$107,0))="","",INDEX('Covenant Tests'!$E$2:$E$107,MATCH($H6,'Covenant Tests'!$J$2:$J$107,0))),"Source record missing") -> Event-driven | D6: =HYPERLINK("#'Covenant Tests'!A"&(MATCH($H6,'Covenant Tests'!$J$2:$J$107,0)+1),INDEX('Covenant Tests'!$C$2:$C$107,MATCH($H6,'Covenant Tests'!$J$2:$J$107,0))) -> Interest reserve top-up | E6: =IFERROR(IF(INDEX('Covenant Tests'!$D$2:$D$107,MATCH($H6,'Covenant Tests'!$J$2:$J$107,0))="","",INDEX('Covenant Tests'!$D$2:$D$107,MATCH($H6,'Covenant Tests'!$J$2:$J$107,0))),"Source record missing") -> Reserve short of projected current pay interest, or loan to cost at 70% | F6: =IFERROR(IF(INDEX('Covenant Tests'!$G$2:$G$107,MATCH($H6,'Covenant Tests'!$J$2:$J$107,0))="","",INDEX('Covenant Tests'!$G$2:$G$107,MATCH($H6,'Covenant Tests'!$J$2:$J$107,0))),"Source record missing") -> On lender notice | G6: =IFERROR(IF(INDEX('Covenant Tests'!$I$2:$I$107,MATCH($H6,'Covenant Tests'!$J$2:$J$107,0))="","",INDEX('Covenant Tests'!$I$2:$I$107,MATCH($H6,'Covenant Tests'!$J$2:$J$107,0))),"Source record missing") -> Loan Agreement 3.4(d) | H6: CT004
A7: =IFERROR(IF(INDEX('Covenant Tests'!$A$2:$A$107,MATCH($H7,'Covenant Tests'!$J$2:$J$107,0))="","",INDEX('Covenant Tests'!$A$2:$A$107,MATCH($H7,'Covenant Tests'!$J$2:$J$107,0))),"Source record missing") -> Spectrum Loop | B7: =IFERROR(IF(INDEX('Covenant Tests'!$B$2:$B$107,MATCH($H7,'Covenant Tests'!$J$2:$J$107,0))="","",INDEX('Covenant Tests'!$B$2:$B$107,MATCH($H7,'Covenant Tests'!$J$2:$J$107,0))),"Source record missing") -> Nationwide | C7: =IFERROR(IF(INDEX('Covenant Tests'!$E$2:$E$107,MATCH($H7,'Covenant Tests'!$J$2:$J$107,0))="","",INDEX('Covenant Tests'!$E$2:$E$107,MATCH($H7,'Covenant Tests'!$J$2:$J$107,0))),"Source record missing") -> Ongoing | D7: =HYPERLINK("#'Covenant Tests'!A"&(MATCH($H7,'Covenant Tests'!$J$2:$J$107,0)+1),INDEX('Covenant Tests'!$C$2:$C$107,MATCH($H7,'Covenant Tests'!$J$2:$J$107,0))) -> Cash sweep and distribution block | E7: =IFERROR(IF(INDEX('Covenant Tests'!$D$2:$D$107,MATCH($H7,'Covenant Tests'!$J$2:$J$107,0))="","",INDEX('Covenant Tests'!$D$2:$D$107,MATCH($H7,'Covenant Tests'!$J$2:$J$107,0))),"Source record missing") -> Until final completion, DSCR 1.00x on trailing 3 months and capitalized interest repaid | F7: =IFERROR(IF(INDEX('Covenant Tests'!$G$2:$G$107,MATCH($H7,'Covenant Tests'!$J$2:$J$107,0))="","",INDEX('Covenant Tests'!$G$2:$G$107,MATCH($H7,'Covenant Tests'!$J$2:$J$107,0))),"Source record missing") -> Ongoing; monthly | G7: =IFERROR(IF(INDEX('Covenant Tests'!$I$2:$I$107,MATCH($H7,'Covenant Tests'!$J$2:$J$107,0))="","",INDEX('Covenant Tests'!$I$2:$I$107,MATCH($H7,'Covenant Tests'!$J$2:$J$107,0))),"Source record missing") -> Loan Agreement 3.5, 7.14 | H7: CT005
A8: =IFERROR(IF(INDEX('Covenant Tests'!$A$2:$A$107,MATCH($H8,'Covenant Tests'!$J$2:$J$107,0))="","",INDEX('Covenant Tests'!$A$2:$A$107,MATCH($H8,'Covenant Tests'!$J$2:$J$107,0))),"Source record missing") -> Spectrum Loop | B8: =IFERROR(IF(INDEX('Covenant Tests'!$B$2:$B$107,MATCH($H8,'Covenant Tests'!$J$2:$J$107,0))="","",INDEX('Covenant Tests'!$B$2:$B$107,MATCH($H8,'Covenant Tests'!$J$2:$J$107,0))),"Source record missing") -> Nationwide | C8: =IFERROR(IF(INDEX('Covenant Tests'!$E$2:$E$107,MATCH($H8,'Covenant Tests'!$J$2:$J$107,0))="","",INDEX('Covenant Tests'!$E$2:$E$107,MATCH($H8,'Covenant Tests'!$J$2:$J$107,0))),"Source record missing") -> Event-driven | D8: =HYPERLINK("#'Covenant Tests'!A"&(MATCH($H8,'Covenant Tests'!$J$2:$J$107,0)+1),INDEX('Covenant Tests'!$C$2:$C$107,MATCH($H8,'Covenant Tests'!$J$2:$J$107,0))) -> Interest reserve top-up | E8: =IFERROR(IF(INDEX('Covenant Tests'!$D$2:$D$107,MATCH($H8,'Covenant Tests'!$J$2:$J$107,0))="","",INDEX('Covenant Tests'!$D$2:$D$107,MATCH($H8,'Covenant Tests'!$J$2:$J$107,0))),"Source record missing") -> Reserve short of projected current pay interest, or loan to cost at 70% | F8: =IFERROR(IF(INDEX('Covenant Tests'!$G$2:$G$107,MATCH($H8,'Covenant Tests'!$J$2:$J$107,0))="","",INDEX('Covenant Tests'!$G$2:$G$107,MATCH($H8,'Covenant Tests'!$J$2:$J$107,0))),"Source record missing") -> On lender notice | G8: =IFERROR(IF(INDEX('Covenant Tests'!$I$2:$I$107,MATCH($H8,'Covenant Tests'!$J$2:$J$107,0))="","",INDEX('Covenant Tests'!$I$2:$I$107,MATCH($H8,'Covenant Tests'!$J$2:$J$107,0))),"Source record missing") -> Loan Agreement 3.4(d) | H8: CT006
A9: =IFERROR(IF(INDEX('Covenant Tests'!$A$2:$A$107,MATCH($H9,'Covenant Tests'!$J$2:$J$107,0))="","",INDEX('Covenant Tests'!$A$2:$A$107,MATCH($H9,'Covenant Tests'!$J$2:$J$107,0))),"Source record missing") -> Fort Collins Vine | B9: =IFERROR(IF(INDEX('Covenant Tests'!$B$2:$B$107,MATCH($H9,'Covenant Tests'!$J$2:$J$107,0))="","",INDEX('Covenant Tests'!$B$2:$B$107,MATCH($H9,'Covenant Tests'!$J$2:$J$107,0))),"Source record missing") -> Western-Southern | C9: =IFERROR(IF(INDEX('Covenant Tests'!$E$2:$E$107,MATCH($H9,'Covenant Tests'!$J$2:$J$107,0))="","",INDEX('Covenant Tests'!$E$2:$E$107,MATCH($H9,'Covenant Tests'!$J$2:$J$107,0))),"Source record missing") -> Ongoing | D9: =HYPERLINK("#'Covenant Tests'!A"&(MATCH($H9,'Covenant Tests'!$J$2:$J$107,0)+1),INDEX('Covenant Tests'!$C$2:$C$107,MATCH($H9,'Covenant Tests'!$J$2:$J$107,0))) -> Stabilization: NOI | E9: =IFERROR(IF(INDEX('Covenant Tests'!$D$2:$D$107,MATCH($H9,'Covenant Tests'!$J$2:$J$107,0))="","",INDEX('Covenant Tests'!$D$2:$D$107,MATCH($H9,'Covenant Tests'!$J$2:$J$107,0))),"Source record missing") -> $6,775,000 annualized for three straight months | F9: =IFERROR(IF(INDEX('Covenant Tests'!$G$2:$G$107,MATCH($H9,'Covenant Tests'!$J$2:$J$107,0))="","",INDEX('Covenant Tests'!$G$2:$G$107,MATCH($H9,'Covenant Tests'!$J$2:$J$107,0))),"Source record missing") -> Ongoing; until met, by June 2028 | G9: =IFERROR(IF(INDEX('Covenant Tests'!$I$2:$I$107,MATCH($H9,'Covenant Tests'!$J$2:$J$107,0))="","",INDEX('Covenant Tests'!$I$2:$I$107,MATCH($H9,'Covenant Tests'!$J$2:$J$107,0))),"Source record missing") -> Stabilization Guaranty; Note 5.6 | H9: CT012
A10: =IFERROR(IF(INDEX('Covenant Tests'!$A$2:$A$107,MATCH($H10,'Covenant Tests'!$J$2:$J$107,0))="","",INDEX('Covenant Tests'!$A$2:$A$107,MATCH($H10,'Covenant Tests'!$J$2:$J$107,0))),"Source record missing") -> Ellenton | B10: =IFERROR(IF(INDEX('Covenant Tests'!$B$2:$B$107,MATCH($H10,'Covenant Tests'!$J$2:$J$107,0))="","",INDEX('Covenant Tests'!$B$2:$B$107,MATCH($H10,'Covenant Tests'!$J$2:$J$107,0))),"Source record missing") -> Kayne Anderson | C10: =IFERROR(IF(INDEX('Covenant Tests'!$E$2:$E$107,MATCH($H10,'Covenant Tests'!$J$2:$J$107,0))="","",INDEX('Covenant Tests'!$E$2:$E$107,MATCH($H10,'Covenant Tests'!$J$2:$J$107,0))),"Source record missing") -> Event-driven | D10: =HYPERLINK("#'Covenant Tests'!A"&(MATCH($H10,'Covenant Tests'!$J$2:$J$107,0)+1),INDEX('Covenant Tests'!$C$2:$C$107,MATCH($H10,'Covenant Tests'!$J$2:$J$107,0))) -> Interest reserve replenishment | E10: =IFERROR(IF(INDEX('Covenant Tests'!$D$2:$D$107,MATCH($H10,'Covenant Tests'!$J$2:$J$107,0))="","",INDEX('Covenant Tests'!$D$2:$D$107,MATCH($H10,'Covenant Tests'!$J$2:$J$107,0))),"Source record missing") -> Lesser of the deficiency or the amount to reach 1.0x Implied DSCR | F10: =IFERROR(IF(INDEX('Covenant Tests'!$G$2:$G$107,MATCH($H10,'Covenant Tests'!$J$2:$J$107,0))="","",INDEX('Covenant Tests'!$G$2:$G$107,MATCH($H10,'Covenant Tests'!$J$2:$J$107,0))),"Source record missing") -> On lender notice | G10: =IFERROR(IF(INDEX('Covenant Tests'!$I$2:$I$107,MATCH($H10,'Covenant Tests'!$J$2:$J$107,0))="","",INDEX('Covenant Tests'!$I$2:$I$107,MATCH($H10,'Covenant Tests'!$J$2:$J$107,0))),"Source record missing") -> Loan Agreement 6.1(b) | H10: CT017
A11: =IFERROR(IF(INDEX('Covenant Tests'!$A$2:$A$107,MATCH($H11,'Covenant Tests'!$J$2:$J$107,0))="","",INDEX('Covenant Tests'!$A$2:$A$107,MATCH($H11,'Covenant Tests'!$J$2:$J$107,0))),"Source record missing") -> Panama City Beach | B11: =IFERROR(IF(INDEX('Covenant Tests'!$B$2:$B$107,MATCH($H11,'Covenant Tests'!$J$2:$J$107,0))="","",INDEX('Covenant Tests'!$B$2:$B$107,MATCH($H11,'Covenant Tests'!$J$2:$J$107,0))),"Source record missing") -> Merchants Bank of Indiana | C11: =IFERROR(IF(INDEX('Covenant Tests'!$E$2:$E$107,MATCH($H11,'Covenant Tests'!$J$2:$J$107,0))="","",INDEX('Covenant Tests'!$E$2:$E$107,MATCH($H11,'Covenant Tests'!$J$2:$J$107,0))),"Source record missing") -> Ongoing | D11: =HYPERLINK("#'Covenant Tests'!A"&(MATCH($H11,'Covenant Tests'!$J$2:$J$107,0)+1),INDEX('Covenant Tests'!$C$2:$C$107,MATCH($H11,'Covenant Tests'!$J$2:$J$107,0))) -> Rent collection escrow release | E11: =IFERROR(IF(INDEX('Covenant Tests'!$D$2:$D$107,MATCH($H11,'Covenant Tests'!$J$2:$J$107,0))="","",INDEX('Covenant Tests'!$D$2:$D$107,MATCH($H11,'Covenant Tests'!$J$2:$J$107,0))),"Source record missing") -> DSCR 1.20x and $509,914 monthly rent collections, 3 straight months | F11: =IFERROR(IF(INDEX('Covenant Tests'!$G$2:$G$107,MATCH($H11,'Covenant Tests'!$J$2:$J$107,0))="","",INDEX('Covenant Tests'!$G$2:$G$107,MATCH($H11,'Covenant Tests'!$J$2:$J$107,0))),"Source record missing") -> Ongoing; until released | G11: =IFERROR(IF(INDEX('Covenant Tests'!$I$2:$I$107,MATCH($H11,'Covenant Tests'!$J$2:$J$107,0))="","",INDEX('Covenant Tests'!$I$2:$I$107,MATCH($H11,'Covenant Tests'!$J$2:$J$107,0))),"Source record missing") -> Loan Agreement 6.2 | H11: CT018
A12: =IFERROR(IF(INDEX('Covenant Tests'!$A$2:$A$107,MATCH($H12,'Covenant Tests'!$J$2:$J$107,0))="","",INDEX('Covenant Tests'!$A$2:$A$107,MATCH($H12,'Covenant Tests'!$J$2:$J$107,0))),"Source record missing") -> Port St Lucie | B12: =IFERROR(IF(INDEX('Covenant Tests'!$B$2:$B$107,MATCH($H12,'Covenant Tests'!$J$2:$J$107,0))="","",INDEX('Covenant Tests'!$B$2:$B$107,MATCH($H12,'Covenant Tests'!$J$2:$J$107,0))),"Source record missing") -> Blackstone / FGL | C12: =IFERROR(IF(INDEX('Covenant Tests'!$E$2:$E$107,MATCH($H12,'Covenant Tests'!$J$2:$J$107,0))="","",INDEX('Covenant Tests'!$E$2:$E$107,MATCH($H12,'Covenant Tests'!$J$2:$J$107,0))),"Source record missing") -> Ongoing | D12: =HYPERLINK("#'Covenant Tests'!A"&(MATCH($H12,'Covenant Tests'!$J$2:$J$107,0)+1),INDEX('Covenant Tests'!$C$2:$C$107,MATCH($H12,'Covenant Tests'!$J$2:$J$107,0))) -> Cash trap since closing | E12: =IFERROR(IF(INDEX('Covenant Tests'!$D$2:$D$107,MATCH($H12,'Covenant Tests'!$J$2:$J$107,0))="","",INDEX('Covenant Tests'!$D$2:$D$107,MATCH($H12,'Covenant Tests'!$J$2:$J$107,0))),"Source record missing") -> Released at NOI of $3,000,000 annualized for three straight months | F12: =IFERROR(IF(INDEX('Covenant Tests'!$G$2:$G$107,MATCH($H12,'Covenant Tests'!$J$2:$J$107,0))="","",INDEX('Covenant Tests'!$G$2:$G$107,MATCH($H12,'Covenant Tests'!$J$2:$J$107,0))),"Source record missing") -> Ongoing; until cured | G12: =IFERROR(IF(INDEX('Covenant Tests'!$I$2:$I$107,MATCH($H12,'Covenant Tests'!$J$2:$J$107,0))="","",INDEX('Covenant Tests'!$I$2:$I$107,MATCH($H12,'Covenant Tests'!$J$2:$J$107,0))),"Source record missing") -> Loan Agreement 1.1, Cash Trap Event | H12: CT022
A13: =IFERROR(IF(INDEX('Covenant Tests'!$A$2:$A$107,MATCH($H13,'Covenant Tests'!$J$2:$J$107,0))="","",INDEX('Covenant Tests'!$A$2:$A$107,MATCH($H13,'Covenant Tests'!$J$2:$J$107,0))),"Source record missing") -> Port St Lucie | B13: =IFERROR(IF(INDEX('Covenant Tests'!$B$2:$B$107,MATCH($H13,'Covenant Tests'!$J$2:$J$107,0))="","",INDEX('Covenant Tests'!$B$2:$B$107,MATCH($H13,'Covenant Tests'!$J$2:$J$107,0))),"Source record missing") -> Blackstone / FGL | C13: =IFERROR(IF(INDEX('Covenant Tests'!$E$2:$E$107,MATCH($H13,'Covenant Tests'!$J$2:$J$107,0))="","",INDEX('Covenant Tests'!$E$2:$E$107,MATCH($H13,'Covenant Tests'!$J$2:$J$107,0))),"Source record missing") -> Ongoing | D13: =HYPERLINK("#'Covenant Tests'!A"&(MATCH($H13,'Covenant Tests'!$J$2:$J$107,0)+1),INDEX('Covenant Tests'!$C$2:$C$107,MATCH($H13,'Covenant Tests'!$J$2:$J$107,0))) -> Cash Collateral Reserve release | E13: =IFERROR(IF(INDEX('Covenant Tests'!$D$2:$D$107,MATCH($H13,'Covenant Tests'!$J$2:$J$107,0))="","",INDEX('Covenant Tests'!$D$2:$D$107,MATCH($H13,'Covenant Tests'!$J$2:$J$107,0))),"Source record missing") -> Debt Yield 8.25% for two straight quarters | F13: =IFERROR(IF(INDEX('Covenant Tests'!$G$2:$G$107,MATCH($H13,'Covenant Tests'!$J$2:$J$107,0))="","",INDEX('Covenant Tests'!$G$2:$G$107,MATCH($H13,'Covenant Tests'!$J$2:$J$107,0))),"Source record missing") -> Ongoing; until released | G13: =IFERROR(IF(INDEX('Covenant Tests'!$I$2:$I$107,MATCH($H13,'Covenant Tests'!$J$2:$J$107,0))="","",INDEX('Covenant Tests'!$I$2:$I$107,MATCH($H13,'Covenant Tests'!$J$2:$J$107,0))),"Source record missing") -> Loan Agreement 7.5 | H13: CT024
A14: =IFERROR(IF(INDEX('Covenant Tests'!$A$2:$A$107,MATCH($H14,'Covenant Tests'!$J$2:$J$107,0))="","",INDEX('Covenant Tests'!$A$2:$A$107,MATCH($H14,'Covenant Tests'!$J$2:$J$107,0))),"Source record missing") -> Port St Lucie | B14: =IFERROR(IF(INDEX('Covenant Tests'!$B$2:$B$107,MATCH($H14,'Covenant Tests'!$J$2:$J$107,0))="","",INDEX('Covenant Tests'!$B$2:$B$107,MATCH($H14,'Covenant Tests'!$J$2:$J$107,0))),"Source record missing") -> Blackstone / FGL | C14: =IFERROR(IF(INDEX('Covenant Tests'!$E$2:$E$107,MATCH($H14,'Covenant Tests'!$J$2:$J$107,0))="","",INDEX('Covenant Tests'!$E$2:$E$107,MATCH($H14,'Covenant Tests'!$J$2:$J$107,0))),"Source record missing") -> Ongoing | D14: =HYPERLINK("#'Covenant Tests'!A"&(MATCH($H14,'Covenant Tests'!$J$2:$J$107,0)+1),INDEX('Covenant Tests'!$C$2:$C$107,MATCH($H14,'Covenant Tests'!$J$2:$J$107,0))) -> Additional Cash Collateral release | E14: =IFERROR(IF(INDEX('Covenant Tests'!$D$2:$D$107,MATCH($H14,'Covenant Tests'!$J$2:$J$107,0))="","",INDEX('Covenant Tests'!$D$2:$D$107,MATCH($H14,'Covenant Tests'!$J$2:$J$107,0))),"Source record missing") -> NOI of $3,000,000 | F14: =IFERROR(IF(INDEX('Covenant Tests'!$G$2:$G$107,MATCH($H14,'Covenant Tests'!$J$2:$J$107,0))="","",INDEX('Covenant Tests'!$G$2:$G$107,MATCH($H14,'Covenant Tests'!$J$2:$J$107,0))),"Source record missing") -> Ongoing; until released | G14: =IFERROR(IF(INDEX('Covenant Tests'!$I$2:$I$107,MATCH($H14,'Covenant Tests'!$J$2:$J$107,0))="","",INDEX('Covenant Tests'!$I$2:$I$107,MATCH($H14,'Covenant Tests'!$J$2:$J$107,0))),"Source record missing") -> Loan Agreement 7.5 | H14: CT025
A15: =IFERROR(IF(INDEX('Covenant Tests'!$A$2:$A$107,MATCH($H15,'Covenant Tests'!$J$2:$J$107,0))="","",INDEX('Covenant Tests'!$A$2:$A$107,MATCH($H15,'Covenant Tests'!$J$2:$J$107,0))),"Source record missing") -> St. Augustine | B15: =IFERROR(IF(INDEX('Covenant Tests'!$B$2:$B$107,MATCH($H15,'Covenant Tests'!$J$2:$J$107,0))="","",INDEX('Covenant Tests'!$B$2:$B$107,MATCH($H15,'Covenant Tests'!$J$2:$J$107,0))),"Source record missing") -> Simmons | C15: =IFERROR(IF(INDEX('Covenant Tests'!$E$2:$E$107,MATCH($H15,'Covenant Tests'!$J$2:$J$107,0))="","",INDEX('Covenant Tests'!$E$2:$E$107,MATCH($H15,'Covenant Tests'!$J$2:$J$107,0))),"Source record missing") -> Ongoing | D15: =HYPERLINK("#'Covenant Tests'!A"&(MATCH($H15,'Covenant Tests'!$J$2:$J$107,0)+1),INDEX('Covenant Tests'!$C$2:$C$107,MATCH($H15,'Covenant Tests'!$J$2:$J$107,0))) -> Cash trap before stabilization | E15: =IFERROR(IF(INDEX('Covenant Tests'!$D$2:$D$107,MATCH($H15,'Covenant Tests'!$J$2:$J$107,0))="","",INDEX('Covenant Tests'!$D$2:$D$107,MATCH($H15,'Covenant Tests'!$J$2:$J$107,0))),"Source record missing") -> Released at DSCR 1.20x | F15: =IFERROR(IF(INDEX('Covenant Tests'!$G$2:$G$107,MATCH($H15,'Covenant Tests'!$J$2:$J$107,0))="","",INDEX('Covenant Tests'!$G$2:$G$107,MATCH($H15,'Covenant Tests'!$J$2:$J$107,0))),"Source record missing") -> Ongoing; until Initial Stabilization | G15: =IFERROR(IF(INDEX('Covenant Tests'!$I$2:$I$107,MATCH($H15,'Covenant Tests'!$J$2:$J$107,0))="","",INDEX('Covenant Tests'!$I$2:$I$107,MATCH($H15,'Covenant Tests'!$J$2:$J$107,0))),"Source record missing") -> Loan Agreement 10.21 | H15: CT030
A16: =IFERROR(IF(INDEX('Covenant Tests'!$A$2:$A$107,MATCH($H16,'Covenant Tests'!$J$2:$J$107,0))="","",INDEX('Covenant Tests'!$A$2:$A$107,MATCH($H16,'Covenant Tests'!$J$2:$J$107,0))),"Source record missing") -> St. Augustine | B16: =IFERROR(IF(INDEX('Covenant Tests'!$B$2:$B$107,MATCH($H16,'Covenant Tests'!$J$2:$J$107,0))="","",INDEX('Covenant Tests'!$B$2:$B$107,MATCH($H16,'Covenant Tests'!$J$2:$J$107,0))),"Source record missing") -> Simmons | C16: =IFERROR(IF(INDEX('Covenant Tests'!$E$2:$E$107,MATCH($H16,'Covenant Tests'!$J$2:$J$107,0))="","",INDEX('Covenant Tests'!$E$2:$E$107,MATCH($H16,'Covenant Tests'!$J$2:$J$107,0))),"Source record missing") -> Event-driven | D16: =HYPERLINK("#'Covenant Tests'!A"&(MATCH($H16,'Covenant Tests'!$J$2:$J$107,0)+1),INDEX('Covenant Tests'!$C$2:$C$107,MATCH($H16,'Covenant Tests'!$J$2:$J$107,0))) -> Cash trap after stabilization | E16: =IFERROR(IF(INDEX('Covenant Tests'!$D$2:$D$107,MATCH($H16,'Covenant Tests'!$J$2:$J$107,0))="","",INDEX('Covenant Tests'!$D$2:$D$107,MATCH($H16,'Covenant Tests'!$J$2:$J$107,0))),"Source record missing") -> DSCR under 1.15x for 3 straight months | F16: =IFERROR(IF(INDEX('Covenant Tests'!$G$2:$G$107,MATCH($H16,'Covenant Tests'!$J$2:$J$107,0))="","",INDEX('Covenant Tests'!$G$2:$G$107,MATCH($H16,'Covenant Tests'!$J$2:$J$107,0))),"Source record missing") -> After stabilization; monthly | G16: =IFERROR(IF(INDEX('Covenant Tests'!$I$2:$I$107,MATCH($H16,'Covenant Tests'!$J$2:$J$107,0))="","",INDEX('Covenant Tests'!$I$2:$I$107,MATCH($H16,'Covenant Tests'!$J$2:$J$107,0))),"Source record missing") -> Loan Agreement 10.21 | H16: CT031
... A30: =IFERROR(IF(INDEX('Covenant Tests'!$A$2:$A$107,MATCH($H30,'Covenant Tests'!$J$2:$J$107,0))="","",INDEX('Covenant Tests'!$A$2:$A$107,MATCH($H30,'Covenant Tests'!$J$2:$J$107,0))),"Source record missing") -> Overland Park | B30: =IFERROR(IF(INDEX('Covenant Tests'!$B$2:$B$107,MATCH($H30,'Covenant Tests'!$J$2:$J$107,0))="","",INDEX('Covenant Tests'!$B$2:$B$107,MATCH($H30,'Covenant Tests'!$J$2:$J$107,0))),"Source record missing") -> Simmons | C30: =IFERROR(IF(INDEX('Covenant Tests'!$E$2:$E$107,MATCH($H30,'Covenant Tests'!$J$2:$J$107,0))="","",INDEX('Covenant Tests'!$E$2:$E$107,MATCH($H30,'Covenant Tests'!$J$2:$J$107,0))),"Source record missing") -> Ongoing | D30: =HYPERLINK("#'Covenant Tests'!A"&(MATCH($H30,'Covenant Tests'!$J$2:$J$107,0)+1),INDEX('Covenant Tests'!$C$2:$C$107,MATCH($H30,'Covenant Tests'!$J$2:$J$107,0))) -> Loan to cost | E30: =IFERROR(IF(INDEX('Covenant Tests'!$D$2:$D$107,MATCH($H30,'Covenant Tests'!$J$2:$J$107,0))="","",INDEX('Covenant Tests'!$D$2:$D$107,MATCH($H30,'Covenant Tests'!$J$2:$J$107,0))),"Source record missing") -> 65% of project cost | F30: =IFERROR(IF(INDEX('Covenant Tests'!$G$2:$G$107,MATCH($H30,'Covenant Tests'!$J$2:$J$107,0))="","",INDEX('Covenant Tests'!$G$2:$G$107,MATCH($H30,'Covenant Tests'!$J$2:$J$107,0))),"Source record missing") -> At all times | G30: =IFERROR(IF(INDEX('Covenant Tests'!$I$2:$I$107,MATCH($H30,'Covenant Tests'!$J$2:$J$107,0))="","",INDEX('Covenant Tests'!$I$2:$I$107,MATCH($H30,'Covenant Tests'!$J$2:$J$107,0))),"Source record missing") -> Loan Agreement, Loan to Cost | H30: CT103

Sheet Covenant Tests
A1: Property | B1: Lender | C1: Test | D1: Threshold | E1: Timing Type | F1: First Test Date | G1: Timing / Frequency | H1: In 2027 | I1: Reference | J1: Covenant ID
A2: Dove Valley | B2: Nationwide | C2: Extension: Net Cash Flow coverage | D2: 105% of interest at the 8.50% Base Rate | E2: One-time | F2: 46692 | G2: Once | H2: Yes | I2: Loan Agreement 3.7(g) | J2: CT001
A3: Dove Valley | B3: Nationwide | C3: Extension: LTV | D3: 65% of fair market value | E3: One-time | F3: 46692 | G3: Once | H3: Yes | I3: Loan Agreement 3.7(f) | J3: CT002
A4: Dove Valley | B4: Nationwide | C4: Cash sweep and distribution block | D4: Until final completion, DSCR 1.00x on trailing 3 months and capitalized interest repaid | E4: Ongoing | G4: Ongoing; monthly | H4: Yes | I4: Loan Agreement 3.5, 7.14 | J4: CT003
A5: Dove Valley | B5: Nationwide | C5: Interest reserve top-up | D5: Reserve short of projected current pay interest, or loan to cost at 70% | E5: Event-driven | G5: On lender notice | H5: Yes | I5: Loan Agreement 3.4(d) | J5: CT004
A6: Spectrum Loop | B6: Nationwide | C6: Cash sweep and distribution block | D6: Until final completion, DSCR 1.00x on trailing 3 months and capitalized interest repaid | E6: Ongoing | G6: Ongoing; monthly | H6: Yes | I6: Loan Agreement 3.5, 7.14 | J6: CT005
A7: Spectrum Loop | B7: Nationwide | C7: Interest reserve top-up | D7: Reserve short of projected current pay interest, or loan to cost at 70% | E7: Event-driven | G7: On lender notice | H7: Yes | I7: Loan Agreement 3.4(d) | J7: CT006
A8: Spectrum Loop | B8: Nationwide | C8: Extension: Net Cash Flow coverage | D8: 105% of interest at the 8.25% Base Rate | E8: One-time | F8: 47014 | G8: Once | H8: No | I8: Loan Agreement 3.7(g) | J8: CT007
A9: Spectrum Loop | B9: Nationwide | C9: Extension: LTV | D9: 66% of fair market value | E9: One-time | F9: 47014 | G9: Once | H9: No | I9: Loan Agreement 3.7(f) | J9: CT008
A10: Fort Collins Shields | B10: Starwood | C10: Cash trap: Debt Yield | D10: 6.50% (6.75% for two straight quarters to release) | E10: Recurring | F10: 46608 | G10: Quarterly from the August 2027 payment date | H10: Yes | I10: Loan Agreement 1.1, Cash Management Event | J10: CT009
A11: Fort Collins Shields | B11: Starwood | C11: First extension: Debt Yield | D11: 7.00% | E11: One-time | F11: 46974 | G11: Once | H11: No | I11: Loan Agreement 2.2.8(c) | J11: CT010
A12: Fort Collins Shields | B12: Starwood | C12: Second extension: Debt Yield | D12: 7.25% | E12: One-time | F12: 47339 | G12: Once | H12: No | I12: Loan Agreement 2.2.8(d) | J12: CT011
A13: Fort Collins Vine | B13: Western-Southern | C13: Stabilization: NOI | D13: $6,775,000 annualized for three straight months | E13: Ongoing | G13: Ongoing; until met, by June 2028 | H13: Yes | I13: Stabilization Guaranty; Note 5.6 | J13: CT012
A14: Fort Collins Vine | B14: Western-Southern | C14: Paydown test: Debt Yield | D14: 9.75% as of 6/30/2028, unless Stabilization is met | E14: One-time | F14: 46934 | G14: Once | H14: No | I14: Note 5.6 | J14: CT013
A15: Ellenton | B15: Kayne Anderson | C15: Debt Yield | D15: 6.00% (7.00% to release) | E15: Recurring | F15: 46660 | G15: Quarterly | H15: Yes | I15: Loan Agreement 2.5(a) | J15: CT014
A16: Ellenton | B16: Kayne Anderson | C16: Implied DSCR | D16: 1.00x (1.05x to release) | E16: Recurring | F16: 46660 | G16: Quarterly | H16: Yes | I16: Loan Agreement 2.5(b) | J16: CT015
A17: Ellenton | B17: Kayne Anderson | C17: Extension: Debt Yield | D17: 7.00% first extension, 7.25% second | E17: Recurring | F17: 47266 | G17: Each extension | H17: No | I17: Loan Agreement 2.3.3 | J17: CT016
A18: Ellenton | B18: Kayne Anderson | C18: Interest reserve replenishment | D18: Lesser of the deficiency or the amount to reach 1.0x Implied DSCR | E18: Event-driven | G18: On lender notice | H18: Yes | I18: Loan Agreement 6.1(b) | J18: CT017
A19: Panama City Beach | B19: Merchants Bank of Indiana | C19: Rent collection escrow release | D19: DSCR 1.20x and $509,914 monthly rent collections, 3 straight months | E19: Ongoing | G19: Ongoing; until released | H19: Yes | I19: Loan Agreement 6.2 | J19: CT018
A20: Ponte Vedra | B20: Trustmark | C20: DSCR covenant | D20: 1.00x | E20: Recurring | F20: 46996 | G20: From 8/31/2028 | H20: No | I20: Loan Agreement 6.28 | J20: CT019
A21: Ponte Vedra | B21: Trustmark | C21: Extension: DSCR | D21: 1.25x | E21: One-time | F21: 47149 | G21: Once | H21: No | I21: Loan Agreement 2.2(c), 6.28 | J21: CT020
A22: Ponte Vedra | B22: Trustmark | C22: Extension: LTV | D22: 61% of as-is value | E22: One-time | F22: 47162 | G22: Once | H22: No | I22: Loan Agreement 2.2(c) | J22: CT021
A23: Port St Lucie | B23: Blackstone / FGL | C23: Cash trap since closing | D23: Released at NOI of $3,000,000 annualized for three straight months | E23: Ongoing | G23: Ongoing; until cured | H23: Yes | I23: Loan Agreement 1.1, Cash Trap Event | J23: CT022
A24: Port St Lucie | B24: Blackstone / FGL | C24: Cash trap: Debt Yield and DSCR | D24: 8.00% and 1.25x (8.50% and 1.35x after 9/1/2028) | E24: Recurring | F24: 46477 | G24: Quarterly | H24: Yes | I24: Loan Agreement 1.1, Cash Trap Event | J24: CT023
A25: Port St Lucie | B25: Blackstone / FGL | C25: Cash Collateral Reserve release | D25: Debt Yield 8.25% for two straight quarters | E25: Ongoing | G25: Ongoing; until released | H25: Yes | I25: Loan Agreement 7.5 | J25: CT024
A26: Port St Lucie | B26: Blackstone / FGL | C26: Additional Cash Collateral release | D26: NOI of $3,000,000 | E26: Ongoing | G26: Ongoing; until released | H26: Yes | I26: Loan Agreement 7.5 | J26: CT025
A27: Port St Lucie | B27: Blackstone / FGL | C27: First extension: Debt Yield | D27: 8.50% | E27: One-time | F27: 46997 | G27: Once | H27: No | I27: Loan Agreement 2.9 | J27: CT026
A28: Port St Lucie | B28: Blackstone / FGL | C28: Second extension: Debt Yield | D28: 9.00% | E28: One-time | F28: 47362 | G28: Once | H28: No | I28: Loan Agreement 2.9 | J28: CT027
A29: Sarasota | B29: Stifel | C29: DSCR covenant | D29: 1.20x | E29: Event-driven | G29: After maturity; each 12/31 and 6/30 from 7/1/2026 | H29: No | I29: Loan Agreement 11.1 | J29: CT028
A30: St. Augustine | B30: Simmons | C30: DSCR covenant | D30: 1.35x | E30: Recurring | F30: 46203 | G30: Quarterly; trailing 3, 6, 9, then 12 months | H30: Yes | I30: Loan Agreement, Events of Default | J30: CT029
A31: St. Augustine | B31: Simmons | C31: Cash trap before stabilization | D31: Released at DSCR 1.20x | E31: Ongoing | G31: Ongoing; until Initial Stabilization | H31: Yes | I31: Loan Agreement 10.21 | J31: CT030
A32: St. Augustine | B32: Simmons | C32: Cash trap after stabilization | D32: DSCR under 1.15x for 3 straight months | E32: Event-driven | G32: After stabilization; monthly | H32: Check | I32: Loan Agreement 10.21 | J32: CT031
A33: St. Augustine | B33: Simmons | C33: Loan to cost | D33: 57.50% of project cost | E33: Ongoing | G33: At all times | H33: Yes | I33: Loan Agreement, Loan to Cost | J33: CT032
A34: St. Augustine | B34: Simmons | C34: Distribution block | D34: No distributions until the loan is repaid, except tax distributions | E34: Ongoing | G34: At all times | H34: Yes | I34: Loan Agreement, Distributions | J34: CT033
A35: St. Augustine | B35: Simmons | C35: Extension: DSCR | D35: 1.25x | E35: One-time | F35: 46748 | G35: Once | H35: Yes | I35: Note, Extension | J35: CT034
A36: St. Augustine | B36: Simmons | C36: Extension: LTV | D36: 55% of as-is value | E36: One-time | F36: 46748 | G36: Once | H36: Yes | I36: Note, Extension | J36: CT035
A37: Venice | B37: UMB | C37: DSCR covenant | D37: 1.10x | E37: Recurring | F37: 46339 | G37: 11/13/2026, then each 6/30 and 12/31 | H37: Yes | I37: Loan Agreement 5.18 | J37: CT036
A38: Venice | B38: UMB | C38: Occupancy | D38: 87.5% leased | E38: Recurring | F38: 46339 | G38: Semi-annual | H38: Yes | I38: Loan Agreement 5.24 | J38: CT037
A39: Venice | B39: UMB | C39: Extension: DSCR | D39: 1.10x | E39: One-time | F39: 46507 | G39: Once | H39: Yes | I39: Note, Section 1 | J39: CT038
A40: Venice | B40: UMB | C40: Extension: LTV | D40: 70% of as-is value, if bank requires an appraisal | E40: One-time | F40: 46519 | G40: Once | H40: Yes | I40: Note, Section 1 | J40: CT039
A41: Venice | B41: UMB | C41: LTV Threshold | D41: 80% of as-stabilized value | E41: Event-driven | G41: On appraisal; at extension or Event of Default | H41: Yes | I41: Loan Agreement 5.19 | J41: CT040
A42: Venice | B42: UMB | C42: Reserve Account minimum | D42: $1,810,000 | E42: Ongoing | G42: From closing; at all times | H42: Yes | I42: Loan Agreement 5.23 | J42: CT041
A43: Pooler | B43: Fifth Third | C43: DSCR covenant, step one | D43: 1.00x, at rents no lower than the Proforma Rents | E43: Recurring | F43: 46530 | G43: From 5/23/2027 | H43: Yes | I43: Loan Agreement 9.8 | J43: CT042
A44: Pooler | B44: Fifth Third | C44: DSCR covenant, step two | D44: 1.20x | E44: Recurring | F44: 46714 | G44: 11/23/2027 at the latest, then each 6/30 and 12/31 | H44: Yes | I44: Loan Agreement 9.8 | J44: CT043
A45: Pooler | B45: Fifth Third | C45: Extension: DSCR | D45: 1.20x | E45: One-time | F45: 46714 | G45: Once | H45: Yes | I45: Note, Section 8 | J45: CT044
A46: Pooler | B46: Fifth Third | C46: Extension: LTV | D46: 60% of as-is value | E46: One-time | F46: 46714 | G46: Once | H46: Yes | I46: Note, Section 8; Loan Agreement 2.11 | J46: CT045
A47: Pooler | B47: Fifth Third | C47: Distribution test: DSCR | D47: 1.20x on trailing 6 months, annualized | E47: Event-driven | G47: Before distributions; each distribution | H47: Yes | I47: Loan Agreement 9.9 | J47: CT046
A48: Stockbridge | B48: UMB | C48: Occupancy | D48: 50% by 6/27/2027, then 80% from 12/27/2027 | E48: Recurring | F48: 46565 | G48: At all times from 6/27/2027 | H48: Yes | I48: Loan Agreement 7.25 | J48: CT047
A49: Stockbridge | B49: UMB | C49: Extension: DSCR | D49: 1.15x | E49: One-time | F49: 46721 | G49: Once | H49: Yes | I49: Note, Section 2 | J49: CT048
A50: Stockbridge | B50: UMB | C50: DSCR covenant | D50: 1.15x | E50: Recurring | F50: 46748 | G50: 12/27/2027, then each 6/30 and 12/31 | H50: Yes | I50: Loan Agreement 7.20 | J50: CT049
A51: Stockbridge | B51: UMB | C51: LTV Threshold | D51: 60% of as-is value | E51: Event-driven | G51: On appraisal; at extension, after 12/27/2027 or Event of Default | H51: Yes | I51: Loan Agreement 7.21 | J51: CT050
A52: Nampa Sundance | B52: Wintrust | C52: DSCR covenant, step one | D52: 1.00x | E52: One-time | F52: 46507 | G52: Once | H52: Yes | I52: Loan Agreement 9.3 | J52: CT051
A53: Nampa Sundance | B53: Wintrust | C53: IRM Reserve | D53: $500,000 minimum; released with a swap or at DSCR 1.20x | E53: Ongoing | G53: At all times | H53: Yes | I53: Loan Agreement 1.14(b) | J53: CT052
A54: Nampa Sundance | B54: Wintrust | C54: Reappraisal: LTV | D54: 60% | E54: Event-driven | G54: On appraisal; on agent request from 10/3/2027 | H54: Yes | I54: Loan Agreement 4.12 | J54: CT053
A55: Nampa Sundance | B55: Wintrust | C55: Extension: DSCR | D55: 1.20x on trailing 12 months | E55: One-time | F55: 46783 | G55: Once | H55: No | I55: Loan Agreement 1.5 | J55: CT054
A56: Nampa Sundance | B56: Wintrust | C56: DSCR covenant, step two | D56: 1.20x | E56: Recurring | F56: 46873 | G56: 4/30/2028, 10/31/2028, then each 10/31 | H56: No | I56: Loan Agreement 9.3 | J56: CT055
A57: 2022 Fund (Barings) | B57: Barings (2022 Fund) | C57: Cash trap: Portfolio DSCR | D57: 1.05x (two straight quarters to release) | E57: Ongoing | G57: Ongoing; any time after 5/31/2026 | H57: Yes | I57: Loan Agreement 5.5 | J57: CT056
A58: 2022 Fund (Barings) | B58: Barings (2022 Fund) | C58: Interest holdback earnout: Earnout DSCR | D58: 1.15x for the last two quarters | E58: Recurring | F58: 46539 | G58: 6/1/2027 until 6/10/2028 | H58: Yes | I58: Loan Agreement 2.2(b)(ii) | J58: CT057
A59: 2022 Fund (Barings) | B59: Barings (2022 Fund) | C59: First extension: Portfolio Debt Yield | D59: 7.50% | E59: One-time | F59: 46914 | G59: Once | H59: No | I59: Loan Agreement 2.5(b)(i) | J59: CT058
A60: 2022 Fund (Barings) | B60: Barings (2022 Fund) | C60: First extension: Portfolio LTV | D60: 67.5% of appraised value | E60: One-time | F60: 46914 | G60: Once | H60: No | I60: Loan Agreement 2.5(b)(i) | J60: CT059
A61: 2022 Fund (Barings) | B61: Barings (2022 Fund) | C61: Second extension: Portfolio Debt Yield | D61: 7.75% | E61: One-time | F61: 47279 | G61: Once | H61: No | I61: Loan Agreement 2.5(b)(ii) | J61: CT060
A62: 2022 Fund (Barings) | B62: Barings (2022 Fund) | C62: Second extension: Portfolio LTV | D62: 65% of appraised value | E62: One-time | F62: 47279 | G62: Once | H62: No | I62: Loan Agreement 2.5(b)(ii) | J62: CT061
A63: 2023 Fund (Barings) | B63: Barings (2023 Fund) | C63: Cash trap: Portfolio DSCR | D63: 1.05x (two straight quarters to release) | E63: Recurring | F63: 46853 | G63: Any time after 4/10/2028 | H63: No | I63: Loan Agreement 5.5 | J63: CT062
A64: 2023 Fund (Barings) | B64: Barings (2023 Fund) | C64: First extension: Portfolio Debt Yield | D64: 7.50% | E64: One-time | F64: 47401 | G64: Once | H64: No | I64: Loan Agreement 2.5(b)(i) | J64: CT063
A65: 2023 Fund (Barings) | B65: Barings (2023 Fund) | C65: First extension: Portfolio LTV | D65: 70% of appraised value | E65: One-time | F65: 47401 | G65: Once | H65: No | I65: Loan Agreement 2.5(b)(i) | J65: CT064
A66: 2023 Fund (Barings) | B66: Barings (2023 Fund) | C66: Second extension: Portfolio Debt Yield | D66: 8.00% | E66: One-time | F66: 47766 | G66: Once | H66: No | I66: Loan Agreement 2.5(b)(ii) | J66: CT065
A67: 2023 Fund (Barings) | B67: Barings (2023 Fund) | C67: Second extension: Portfolio LTV | D67: 68% of appraised value | E67: One-time | F67: 47766 | G67: Once | H67: No | I67: Loan Agreement 2.5(b)(ii) | J67: CT066
A68: Fayetteville Van Asche | B68: Associated / Trustmark | C68: Extension: DSCR | D68: Pro Forma DSCR 1.20x | E68: One-time | F68: 47280 | G68: Once | H68: No | I68: Loan Agreement 4.3 | J68: CT067
A69: Fayetteville Van Asche | B69: Associated / Trustmark | C69: Extension: LTV | D69: 60% of as-is value, if agent requests | E69: One-time | F69: 47280 | G69: Once | H69: No | I69: Loan Agreement 4.3 | J69: CT068
A70: Fayetteville Van Asche | B70: Associated / Trustmark | C70: DSCR covenant | D70: 1.20x | E70: Recurring | F70: 47483 | G70: Annual, if extended | H70: No | I70: Loan Agreement 8.42 | J70: CT069
A71: Gilbert Val Vista | B71: Nationwide | C71: Cash sweep and distribution block | D71: Until final completion, DSCR 1.00x on trailing 3 months and capitalized interest repaid | E71: Ongoing | G71: Ongoing; monthly | H71: Yes | I71: Loan Agreement 3.5, 7.14 | J71: CT070
A72: Gilbert Val Vista | B72: Nationwide | C72: Interest reserve top-up | D72: Reserve short of projected current pay interest, or loan to cost at 70% | E72: Event-driven | G72: On lender notice | H72: Yes | I72: Loan Agreement 3.4(d) | J72: CT071
A73: Gilbert Val Vista | B73: Nationwide | C73: Extension: Net Cash Flow coverage | D73: 105% of interest at the 7.80% Base Rate | E73: One-time | F73: 47233 | G73: Once | H73: No | I73: Loan Agreement 3.7(g) | J73: CT072
A74: Gilbert Val Vista | B74: Nationwide | C74: Extension: LTV | D74: 65% of fair market value | E74: One-time | F74: 47233 | G74: Once | H74: No | I74: Loan Agreement 3.7(f) | J74: CT073
A75: Venetucci | B75: PNC | C75: Mini perm conversion: DSCR | D75: 1.20x | E75: One-time | F75: 47245 | G75: Once | H75: No | I75: Loan Agreement 2.4 | J75: CT074
A76: Venetucci | B76: PNC | C76: Mini perm conversion: LTV | D76: 60% of as-is value | E76: One-time | F76: 47245 | G76: Once | H76: No | I76: Loan Agreement 2.4 | J76: CT075
A77: Venetucci | B77: PNC | C77: DSCR covenant | D77: 1.25x | E77: Event-driven | G77: After conversion; semi-annual during mini perm | H77: No | I77: Loan Agreement 4.38 | J77: CT076
A78: Longmont Hover | B78: Stifel | C78: DSCR covenant | D78: 1.10x | E78: One-time | F78: 46752 | G78: Once | H78: Yes | I78: Loan Agreement Article 11, Debt Service Coverage Ratio | J78: CT077
A79: Longmont Hover | B79: Stifel | C79: Extension: DSCR | D79: 1.20x | E79: One-time | F79: 46904 | G79: Once | H79: No | I79: Loan Agreement 2.21 | J79: CT078
A80: Monument Higby | B80: UMB | C80: DSCR covenant | D80: 1.20x | E80: Recurring | F80: 47250 | G80: 5/12/2029, then each 6/30 and 12/31 | H80: No | I80: Loan Agreement 7.20 | J80: CT079
A81: Monument Higby | B81: UMB | C81: Extension: DSCR | D81: 1.20x | E81: One-time | F81: 47238 | G81: Once | H81: No | I81: Note, Section 1 | J81: CT080
A82: Monument Higby | B82: UMB | C82: LTV Threshold | D82: 60% of as-stabilized value | E82: Event-driven | G82: On appraisal; at extension or Event of Default | H82: No | I82: Loan Agreement 7.21 | J82: CT081
A83: Wheat Ridge | B83: BOKF / RCB Bank | C83: Extension: DSCR | D83: 1.15x | E83: One-time | F83: 46978 | G83: Once, on 3 months ending Apr to Jun 2028 | H83: No | I83: Loan Agreement 2.6.2 | J83: CT082
A84: Wheat Ridge | B84: BOKF / RCB Bank | C84: Extension: LTV | D84: 60% of appraised value | E84: One-time | F84: 46978 | G84: Once | H84: No | I84: Loan Agreement 2.6.2 | J84: CT083
A85: Wheat Ridge | B85: BOKF / RCB Bank | C85: DSCR covenant | D85: 1.25x (1.35x to release cash collateral) | E85: Recurring | F85: 47118 | G85: Quarterly, if extended | H85: No | I85: Loan Agreement 6.1 | J85: CT084
A86: Buford | B86: BOKF | C86: Extension: DSCR | D86: 1.15x | E86: One-time | F86: 47202 | G86: Once, on 3 months ending Nov 2028 to Jan 2029 | H86: No | I86: Loan Agreement 2.6.2 | J86: CT085
A87: Buford | B87: BOKF | C87: Extension: LTV | D87: 60% of appraised value | E87: One-time | F87: 47202 | G87: Once | H87: No | I87: Loan Agreement 2.6.2 | J87: CT086
A88: Buford | B88: BOKF | C88: DSCR covenant | D88: 1.25x (1.35x to release cash collateral) | E88: Recurring | F88: 47299 | G88: Quarterly, if extended | H88: No | I88: Loan Agreement 6.1 | J88: CT087
A89: Dacula | B89: PNC | C89: Mini perm conversion: DSCR | D89: 1.20x | E89: One-time | F89: 47349 | G89: Once | H89: No | I89: Loan Agreement 2.4 | J89: CT088
A90: Dacula | B90: PNC | C90: Mini perm conversion: LTV | D90: 60% of as-is value | E90: One-time | F90: 47349 | G90: Once | H90: No | I90: Loan Agreement 2.4 | J90: CT089
A91: Dacula | B91: PNC | C91: DSCR covenant | D91: 1.20x | E91: Event-driven | G91: After conversion; semi-annual during mini perm | H91: No | I91: Loan Agreement 4.38 | J91: CT090
A92: Newnan | B92: Comerica | C92: Interest reserve shortfall | D92: IO DSCR under 1.00x and reserve under 90 days of interest | E92: Ongoing | G92: Ongoing; any time | H92: Yes | I92: Loan Agreement 2.4 | J92: CT091
A93: Newnan | B93: Comerica | C93: First extension: DSCR | D93: 1.10x | E93: One-time | G93: June 2029 (day not stated); once | H93: No | I93: Loan Agreement 2.5 | J93: CT092
A94: Newnan | B94: Comerica | C94: Second extension: DSCR | D94: 1.20x | E94: One-time | G94: June 2030 (day not stated); once | H94: No | I94: Loan Agreement 2.6 | J94: CT093
A95: Newnan | B95: Comerica | C95: Reappraisal: LTV | D95: 65% of as-stabilized value | E95: Event-driven | G95: On appraisal; from 90 days before maturity | H95: No | I95: Loan Agreement 6.20 | J95: CT094
A96: Fishers Union | B96: First Internet Bank | C96: Extension: DSCR | D96: 1.15x, whole mixed-use project | E96: One-time | F96: 47087 | G96: Once | H96: No | I96: Loan Agreement 6.4 | J96: CT095
A97: Fishers Union | B97: First Internet Bank | C97: DSCR covenant | D97: 1.20x, whole mixed-use project | E97: Recurring | F97: 47118 | G97: Annual, if extended | H97: No | I97: Loan Agreement 7.3(a) | J97: CT096
A98: Westfield 191st | B98: Fifth Third | C98: DSCR covenant, step one | D98: 1.00x | E98: Recurring | F98: 47118 | G98: From 12/31/2028 | H98: No | I98: Loan Agreement 9.8 | J98: CT097
A99: Westfield 191st | B99: Fifth Third | C99: DSCR covenant, step two | D99: 1.20x | E99: Recurring | F99: 47299 | G99: Each 6/30 and 12/31 | H99: No | I99: Loan Agreement 9.8 | J99: CT098
A100: Westfield 191st | B100: Fifth Third | C100: Extension: DSCR | D100: 1.20x | E100: One-time | F100: 47434 | G100: Once | H100: No | I100: Note, Section 8 | J100: CT099
...

Sheet Test Calculations
A1: Property | B1: Lender | C1: Calc Type | D1: Debt Service | E1: Balance Used | F1: Amortization (Years) | G1: Loan Index | H1: Loan Margin | I1: Loan Rate Floor | J1: Treasury Spread | K1: Sizing Rate | L1: Mortgage Constant | M1: Treasury Rate Source | N1: NOI Period | O1: Revenue | P1: Expenses | Q1: Debt Yield / LTV | R1: Reference
A2: Dove Valley | B2: Nationwide | C2: Fixed rate, interest only | D2: Interest on the loan, including capitalized interest, at the 8.50% Base Rate. Used for the extension and distribution tests. | E2: Outstanding balance, including capitalized interest | G2: Fixed: 8.50% Base Rate | N2: Extension: trailing 12 months. Distributions: trailing 3 months, annualized. | O2: Gross revenues from the project. | P2: Greater of pro forma or actual, with a $200 per unit reserve and the greatest of actual, the appraisal or a 3% management fee. | Q2: LTV: outstanding balance over fair market value, as the lender determines (65%). | R2: Loan Agreement definitions: Net Cash Flow, Operating Expenses, Calendar Period, Debt Service Requirement
A3: Spectrum Loop | B3: Nationwide | C3: Fixed rate, interest only | D3: Interest on the loan, including capitalized interest, at the 8.25% Base Rate. Used for the extension and distribution tests. | E3: Outstanding balance, including capitalized interest | G3: Fixed: 8.25% Base Rate | N3: Extension: trailing 12 months. Distributions: trailing 3 months, annualized. | O3: Gross revenues from the project. | P3: Greater of pro forma or actual, with a $200 per unit reserve and the greatest of actual, the appraisal or a 3% management fee. | Q3: LTV: outstanding balance over fair market value, as the lender determines (66%). | R3: Loan Agreement definitions: Net Cash Flow, Operating Expenses, Calendar Period, Debt Service Requirement
A4: Fort Collins Shields | B4: Starwood | C4: No DSCR test | D4: Not used in the cash trap or extension tests. The rate cap strike resets to hold a 1.10x DSCR. | G4: 1M Term SOFR | H4: 0.023 | N4: Residential revenue: trailing 3 months, annualized. Expenses: trailing 12 months. | O4: Residential income with vacancy at the greater of actual or 5%. | P4: Actual, with the greater of actual or a 3.50% management fee and a $250 per unit reserve. | Q4: Debt Yield: underwritten net cash flow over outstanding principal. | R4: Loan Agreement definitions: Debt Yield, UNCF
A5: Fort Collins Vine | B5: Western-Southern | C5: No DSCR test | D5: Not used. | G5: SOFR | H5: 0.035 | I5: 3.25% index floor; 6.75% all-in floor | N5: Monthly NOI, annualized; three straight months for Stabilization | O5: Residential rent only, capped at 95% occupancy. | P5: Actual, with the greater of actual or a 4% management fee and a $200 per unit reserve. | Q5: Debt Yield: NOI over outstanding principal. A miss is cured by paying down to 9.75%. | R5: Note 5.6; Stabilization Guaranty
A6: Ellenton | B6: Kayne Anderson | C6: Actual debt service | D6: Interest only: principal balance times the actual average rate (SOFR + 2.60%) for the trailing 3 months, net of the rate cap. | E6: Outstanding principal | G6: 1M Term SOFR | H6: 0.026 | I6: 2.75% index floor | N6: Trailing 3 months, annualized | O6: Operating revenue on an accrual basis, capped at 95% physical occupancy. Excludes free rent, concessions and non-recurring revenue. | P6: Actual, with the greater of actual or a 3% management fee and a $250 per unit annual reserve. | Q6: Debt Yield: NOI over principal balance. | R6: Loan Agreement definitions: Adjusted NOI, Implied Debt Service, Debt Yield
A7: Panama City Beach | B7: Merchants Bank of Indiana | C7: Note rate, amortized | D7: Outstanding principal amortized over 30 years at the note rate. | E7: Outstanding principal | F7: 30 | G7: SOFR | H7: 0.0275 | I7: 2.75% all-in floor | N7: Not stated ("specified period") | O7: Net income plus interest, depreciation and amortization, from borrower financial statements. Rent test: gross collections from third-party residential leases, excluding extraordinary income. | P7: As reported, less the replacement reserve amount. | R7: Loan Agreement definitions: Debt Service Coverage Ratio, Debt Service, Monthly Rent Collection Amount
A8: Ponte Vedra | B8: Trustmark | C8: Three-prong rate | D8: Loan amortized over 30 years at the greatest of the actual rate, 7.00%, or 10-year Treasury + 2.50%. | E8: The Loan ($50,000,000 construction loan) | F8: 30 | G8: SOFR | H8: 0.0275 | I8: 1.00% index floor, off while hedged | J8: 0.025 | K8: 0.07 | M8: 10-year US Treasury constant; date not stated | N8: Trailing 3 months, annualized | O8: All operating income of the project. | P8: Operating expenses, management fees and replacement reserves, adjusted so taxes and insurance are not distorted by annualizing. | Q8: LTV: as-is value (61%). | R8: Loan Agreement definitions: Debt Service Coverage Ratio, Net Operating Income; 6.28
A9: Port St Lucie | B9: Blackstone / FGL | C9: Actual debt service | D9: Scheduled principal and interest for the same period. | E9: Scheduled payments | G9: SOFR | H9: 0.0235 | I9: 3.00% index floor | N9: DSCR: trailing 12 months. Debt Yield: NOI as of the test date, using the latest 3 months of expenses. | O9: GAAP income, excluding tenants over 60 days in default, vacating or in free rent, and non-recurring income. | P9: GAAP expenses, adjusted for known changes in the next 12 months (taxes, insurance), with the greater of actual or a 3% management fee. | Q9: Debt Yield: NOI over outstanding principal. | R9: Loan Agreement definitions: Net Operating Income, Gross Income from Operations, Operating Expenses, Debt Yield
A10: Sarasota | B10: Stifel | C10: Three-prong rate | D10: Full $59,900,000 over 30 years at the greater of the loan rate, 6.50%, or 10-year Treasury + 2.25%. | E10: Full $59,900,000 | F10: 30 | G10: Term SOFR | H10: 0.03 | I10: 1.25% index floor | J10: 0.0225 | K10: 0.065 | M10: Fed weekly 10-year constant maturity, 15th day before the test | N10: Trailing 1 month, annualized. Expenses on trailing 12 months. | O10: Gross Operating Income on a cash basis. | P10: Greater of $9,800 per unit or actual, with the higher of actual or a 3% management fee and a $250 per unit reserve. | R10: Loan Agreement definitions: Net Operating Income, Gross Operating Income, Debt Service; 11.1
A11: St. Augustine | B11: Simmons | C11: Actual debt service | D11: Annual principal and interest on the loan. | E11: Scheduled payments | G11: Term SOFR | H11: 0.0325 | I11: 7.00% all-in floor | N11: Trailing 3 months at the first test, then 6, 9 and 12 months | O11: All project revenue. | P11: Normal operating expenses, with the management fee capped at 3.5% of gross income. $150 per unit minimum reserve after stabilization. | Q11: LTV: as-is value (55%). Loan to cost: balance over project cost (57.50%). | R11: Loan Agreement definitions: Net Operating Income, Debt Service Coverage Ratio
A12: Venice | B12: UMB | C12: Three-prong rate | D12: Full $52,250,000 over 30 years at the greatest of the note rate, 10-year Treasury + 2.00%, or 6.75%. | E12: Full $52,250,000 | F12: 30 | G12: 1M Term SOFR | H12: 0.025 | I12: 0.00% index floor | J12: 0.02 | K12: 0.0675 | M12: 10-year Treasury Bond yield; date not stated | N12: 3 months ending on the test date; annualizing is not stated | O12: Actual operating revenue, excluding non-recurring revenue. | P12: Greater of (a) actual, with a $200 per unit reserve and the greater of actual or a 3% management fee, or (b) the closing appraisal's annual estimate. | Q12: LTV: balance plus unfunded over as-stabilized value (80%); as-is value for the extension (70%). | R12: Loan Agreement definitions: Net Operating Income, Operating Expenses, Debt Service; 5.19; Note Section 1
A13: Pooler | B13: Fifth Third | C13: Greater of actual or three-prong rate | D13: Greater of actual principal and interest, or the full $54,250,000 over 30 years at the greatest of the note rate, 7.00%, or 10-year Treasury + 2.50%. | E13: Full $54,250,000 | F13: 30 | G13: 1M Term SOFR | H13: 0.0285 | I13: 0.00% index floor | J13: 0.025 | K13: 0.07 | M13: 10-year Treasury Notes in The Wall Street Journal, 15th day before the test | N13: Trailing 3 months, annualized (6 months for distributions) | O13: Gross revenues on a cash basis, excluding security deposits and prepaid rent. The 1.00x test needs rents at or above the Proforma Rents ($2.44, $1.96 and $2.02 per square foot). | P13: Greater of the appraiser's expenses or actual, with a $200 per unit reserve and the greater of actual or a 3% management fee. | Q13: LTV: as-is value (60% to extend; under Loan Agreement 2.11 the lender can reappraise at extension and resize to 55%). | R13: Loan Agreement definitions: Net Operating Income, Operating Expenses, Debt Service; 9.8
A14: Stockbridge | B14: UMB | C14: Three-prong rate | D14: Loan Amount over 30 years at the greatest of the actual rate, 10-year Treasury + 2.00%, or 7.50%. | E14: Loan Amount ($37,275,630 as defined in the loan agreement; the note says $37,375,630) | F14: 30 | G14: Term SOFR | H14: 0.0275 | I14: 3.00% index floor, off with a swap | J14: 0.02 | K14: 0.075 | M14: 10-year Treasury Bond yield; date not stated | N14: Revenue: trailing 3 months, annualized. Expenses: trailing 6 months, annualized. | O14: All amounts received from the property, excluding non-recurring revenue. | P14: Greater of (a) actual, with a $200 per unit reserve and the greater of actual or a 3% management fee, or (b) the closing appraisal's annual estimate. Taxes fully assessed. | Q14: LTV: balance plus unfunded over as-is value (60%). | R14: Loan Agreement definitions: Net Operating Income, Operating Expenses, Annual Debt Service; 7.21
A15: Nampa Sundance | B15: Wintrust | C15: Note rate plus margin | D15: Interest on the outstanding balance at the note rate + 1.00% (8.00% if a swap is in place). After the first test, add principal on the full $45,600,000 over 30 years. | E15: Interest on the outstanding balance; principal on the full $45,600,000 | F15: 30 | G15: Term SOFR | H15: 0.03 | I15: 0.00% index floor | N15: Tests on 4/30/2027 and 4/30/2028: annualized in-place leases. Later tests and the extension: trailing 12 months. | O15: All project revenue. In-place leases count only tenants in occupancy and paying rent. | P15: Greater of trailing 12 months actual or the stabilized expenses in the closing appraisal. | Q15: LTV: 60% on reappraisal. | R15: Loan Agreement definition: Debt Service Coverage Ratio; 9.3
A16: 2022 Fund (Barings) | B16: Barings (2022 Fund) | C16: Actual debt service | D16: Actual principal and interest for the trailing 3 months, annualized, net of rate cap proceeds. Earnout test: 12 months of interest at the current rate on the Maximum Loan Amount. | E16: Scheduled payments; Maximum Loan Amount for the earnout test | G16: SOFR Index | H16: 0.0225 | I16: 5.25% all-in floor | N16: Revenue: trailing 1 month, annualized. Expenses: trailing 3 months, annualized. All properties combined. | O16: Gross rents and other income, capped at 95% occupancy portfolio-wide. Excludes tenants more than 60 days delinquent and rate cap proceeds. | P16: Actual, with the greater of actual or a 3% management fee, fully assessed taxes and a $250 per unit annual reserve. | Q16: Debt Yield: NOI over outstanding principal. LTV: Maximum Loan Amount over appraised value. | R16: Loan Agreement definitions: Net Operating Income, Operating Revenues, Operating Expenses, Debt Service, Earnout Debt Service
A17: 2023 Fund (Barings) | B17: Barings (2023 Fund) | C17: Actual debt service | D17: Actual principal and interest on all eight loans for the trailing 3 months, annualized, net of rate cap proceeds. | E17: Scheduled payments on all eight loans | G17: SOFR Index | H17: 0.0225 | I17: 5.00% all-in floor | N17: Trailing 3 months, annualized; all eight properties combined | O17: Gross rents and other income, capped at 95% occupancy portfolio-wide. Excludes tenants more than 60 days delinquent and rate cap proceeds. | P17: Actual, with the greater of actual or a 3% management fee, fully assessed taxes and a $250 per unit annual reserve. | Q17: Debt Yield: NOI over aggregate outstanding principal. LTV: Portfolio Maximum Loan Amount over appraised value. | R17: Loan Agreement definitions: Portfolio Net Operating Income, Operating Revenues, Operating Expenses, Portfolio Debt Service
A18: Fayetteville Van Asche | B18: Associated / Trustmark | C18: Three-prong rate | D18: Full commitment ($51,000,000) over 30 years at the greatest of the loan rate, 6.75%, or 10-year Treasury + 2.50%. | E18: Full $51,000,000 commitment | F18: 30 | G18: Term SOFR | H18: 0.0235 | I18: 0.00% index floor | J18: 0.025 | K18: 0.0675 | M18: 10-year Treasury Notes in The Wall Street Journal, 15th day before the test | N18: Extension: last 2 months of income annualized, last 6 months of expenses. Covenant: trailing 12 months at year end. | O18: All actual income, including parking, ancillary, utility billings and miscellaneous. | P18: Actual, adjusted to stabilized: 3% minimum management fee, taxes at full assessment, $150 per unit reserve. | Q18: LTV: principal balance over as-is value (60%). | R18: Loan Agreement definitions: Pro Forma Net Operating Income, Net Operating Income, Pro Forma Debt Service
A19: Gilbert Val Vista | B19: Nationwide | C19: Fixed rate, interest only | D19: Interest on the loan, including capitalized interest, at the 7.80% Base Rate. Used for the extension and distribution tests. | E19: Outstanding balance, including capitalized interest | G19: Fixed: 7.80% Base Rate | N19: Extension: trailing 12 months. Distributions: trailing 3 months, annualized. | O19: Gross revenues from the project. | P19: Greater of pro forma or actual, with a $200 per unit reserve and the greatest of actual, the appraisal or a 3% management fee. | Q19: LTV: outstanding balance over fair market value, as the lender determines (65%). | R19: Loan Agreement definitions: Net Cash Flow, Operating Expenses, Calendar Period, Debt Service Requirement
A20: Venetucci | B20: PNC | C20: Highest of actual, Treasury rate or constant | D20: Highest of actual interest and scheduled principal, a 30-year amortization at 10-year Treasury + 2.00%, or an 8.19% constant, on the commitment amount. | E20: Commitment amount (shown as $66,695,242 in the loan agreement; Loan Terms shows $63,240,018) | F20: 30 | G20: Daily Simple SOFR | H20: 0.0225 | I20: 0.00% floor | J20: 0.02 | L20: 0.0819 | M20: Most recent 10-year Treasury Note yield, as published by the lender | N20: Prior quarter, annualized | O20: Rental income from tenants in occupancy and paying, with a 5% minimum vacancy if occupancy is over 95%, plus other income. | P20: Greatest of the appraisal pro forma, prior quarter annualized, or prior 12 months actual. Includes the greater of actual or a 3% management fee and a $200 per unit reserve. | Q20: LTV: loan amount over as-is value (60%). | R20: Loan Agreement definitions: Revenues, Expenses, Debt Service
A21: Longmont Hover | B21: Stifel | C21: Three-prong rate | D21: Full $63,744,900 over 30 years at the greater of the loan rate, 6.50%, or 10-year Treasury + 2.25%. | E21: Full $63,744,900 | F21: 30 | G21: Term SOFR | H21: 0.03 | I21: 1.25% index floor | J21: 0.0225 | K21: 0.065 | M21: Fed weekly 10-year constant maturity, 15th day before the test | N21: Covenant: trailing 1 month, annualized. Extension: trailing 3 months, annualized. | O21: Gross Operating Income on a cash basis. | P21: Greater of $8,200 per unit or actual, with the higher of actual or a 3% management fee and a $250 per unit reserve. | R21: Loan Agreement definitions: Net Operating Income, Gross Operating Income, Debt Service
A22: Monument Higby | B22: UMB | C22: Three-prong rate | D22: Outstanding loan amount over 30 years at the greatest of the note rate, 10-year Treasury + 2.00%, or 7.00%. | E22: Outstanding loan amount | F22: 30 | G22: Term SOFR | H22: 0.025 | I22: 2.50% index floor, off with a swap | J22: 0.02 | K22: 0.07 | M22: 10-year Treasury Bond yield; date not stated | N22: Revenue: trailing 3 months, annualized. Expenses: trailing 12 months. | O22: All project revenues, excluding non-recurring revenue. | P22: Greater of (a) actual, with a $200 per unit reserve and the greater of actual or a 3% management fee, or (b) the closing appraisal's annual estimate. Taxes fully assessed. | Q22: LTV: balance plus unfunded over as-stabilized value (60%). | R22: Loan Agreement definitions: Net Operating Income, Operating Expenses, Imputed Debt Service; 7.21
A23: Wheat Ridge | B23: BOKF / RCB Bank | C23: Three-prong rate | D23: Outstanding principal over 30 years at the greatest of the note rate, 6.75%, or 10-year Treasury + 2.50%, for the same 3 months. | E23: Outstanding principal | F23: 30 | G23: Term SOFR | H23: 0.0325 | I23: 0.00% index floor | J23: 0.025 | K23: 0.0675 | M23: 10-year U.S. Treasury rate then in effect | N23: 3 months | O23: Gross rental income from leases with tenants in occupancy. No other income. | P23: Actual, excluding income taxes, depreciation and debt service. No management fee or reserve adjustment. | Q23: LTV: loan over new appraised value (60%). | R23: Loan Agreement definitions: Operating Income, Operating Expenses, Debt Service; 2.6.2
A24: Buford | B24: BOKF | C24: Three-prong rate | D24: Outstanding principal over 30 years at the greatest of the note rate, 6.75%, or 10-year Treasury + 2.50%, for the same 3 months. | E24: Outstanding principal | F24: 30 | G24: Term SOFR | H24: 0.025 | I24: 0.00% index floor | J24: 0.025 | K24: 0.0675 | M24: 10-year U.S. Treasury rate then in effect | N24: 3 months | O24: Gross rental income from leases with tenants in occupancy. No other income. | P24: Actual, excluding income taxes, depreciation and debt service. No management fee or reserve adjustment. | Q24: LTV: loan over new appraised value (60%). | R24: Loan Agreement definitions: Operating Income, Operating Expenses, Debt Service; 2.6.2
A25: Dacula | B25: PNC | C25: Highest of actual, Treasury rate or constant | D25: Highest of actual interest and scheduled principal, a 30-year amortization at 10-year Treasury + 2.00%, or a 7.78% constant, on the $55,082,113 commitment. | E25: Full $55,082,113 commitment | F25: 30 | G25: Daily Simple SOFR | H25: 0.02 | I25: 0.00% floor | J25: 0.02 | L25: 0.0778 | M25: Most recent 10-year Treasury Note yield, as published by the lender | N25: Current rent roll annualized, plus the prior month's other income annualized | O25: Rental income from tenants in occupancy and paying, with a 5% minimum vacancy if occupancy is over 95%, plus other income. | P25: Greatest of the appraisal pro forma, prior quarter annualized, or prior 12 months actual. Includes the greater of actual or a 3% management fee and a $200 per unit reserve. | Q25: LTV: loan amount over as-is value (60%). | R25: Loan Agreement definitions: Revenues, Expenses, Debt Service
A26: Newnan | B26: Comerica | C26: Actual debt service | D26: Actual principal and interest for the period. The interest-only ratio uses interest accrued over the 3 months. The 1.15x test that ends the distribution block uses the outstanding balance over 30 years at the greater of the loan rate or 10-year Treasury + 2.00%. | E26: Scheduled payments | G26: Term SOFR | H26: 0.025 | I26: 0.50% index floor | N26: Most recent 3 months, cash basis | O26: Actual rental income and other revenues. | P26: Actual paid plus accrued, plus reserves for taxes, vacancy, insurance and replacements, and a management fee, all as the bank determines. | Q26: LTV: commitment over as-completed, as-stabilized value (65%). | R26: Loan Agreement definitions: Net Operating Income, Debt Service Coverage Ratio, Interest Only Debt Service Coverage Ratio
A27: Fishers Union | B27: First Internet Bank | C27: Actual debt service | D27: Bank's scheduled debt service for the period. The extension test uses principal and interest on a 30-year amortization. | E27: Scheduled payments | F27: 30 | G27: Project loan note not on hand | N27: Period being tested; whole mixed-use project | O27: NOI is not defined in the loan agreement. The extension test uses leases in place. | P27: The extension test uses appraisal expenses. | R27: Loan Agreement definitions: Debt Service Coverage Ratio; 6.4(e)
A28: Westfield 191st | B28: Fifth Third | C28: Greater of actual or three-prong rate | D28: Greater of actual principal and interest, or the full $56,476,922 over 30 years at the greatest of the note rate, 6.50%, or 10-year Treasury + 2.50%. | E28: Full $56,476,922 | F28: 30 | G28: 1M Term SOFR | H28: 0.0225 | I28: 0.00% index floor | J28: 0.025 | K28: 0.065 | M28: 10-year Treasury Notes in The Wall Street Journal, 15th day before the test | N28: Trailing 3 months, annualized (6 months after the guaranty steps down) | O28: Gross revenues actually received, excluding security deposits and prepaid rent. Rents are no less than the Proforma Rents ($2.10, $1.85 and $1.85 per square foot). | P28: Greater of the appraiser's expenses or actual, with a $200 per unit reserve and the greater of actual or a 3% management fee. | Q28: LTV: loan amount over as-is value (60%). | R28: Loan Agreement definitions: Net Operating Income, Operating Expenses, Debt Service; 9.8
A29: Overland Park | B29: Simmons | C29: Actual debt service | D29: Annual principal and interest on the loan. | E29: Scheduled payments | G29: Term SOFR | H29: 0.0275 | I29: 6.00% all-in floor | N29: Revenue: trailing 3 months, annualized. Expenses: trailing 12 months. | O29: Operating revenue from the property, excluding security deposits and interest income. | P29: Normal operating expenses, with the management fee capped at 3% and a $150 per unit minimum reserve. | Q29: Debt Yield: NOI over the full $53,870,265 loan amount. LTV: loan over as-is value (65%). | R29: Loan Agreement definitions: Net Operating Income, Debt Service Coverage Ratio, Debt Yield

Sheet Loan Terms
A1: Property | B1: Lender | C1: Loan Amount | D1: Initial Maturity | E1: Extended Maturity | F1: Guarantor | G1: Payment Guaranty | H1: Non-standard Guarantor Terms | I1: Guarantor Reporting
A2: Dove Valley | B2: Nationwide | C2: 54927747 | D2: 46692 | E2: 47058 | F2: TTHC | G2: Completion and carve-outs only | I2: Quarterly certificate, due in 45 days
A3: Spectrum Loop | B3: Nationwide | C3: 58266493 | D3: 47014 | E3: 47379 | F3: TTHC | G3: Completion and carve-outs only | I3: Quarterly certificate, due in 45 days
A4: Fort Collins Shields | B4: Starwood | C4: 82000000 | D4: 46974 | E4: Aug 2030 | F4: TTHC | G4: Carve-outs only | I4: Quarterly; certified in 60 days
A5: Fort Collins Vine | B5: Western-Southern | C5: 69500000 | D5: 47309 | E5: None | F5: TTHC | G5: Full, until Stabilization (NOI $6,775,000) | H5: Note 5.6 paydown liability capped at $10,250,000 | I5: At all times
A6: Ellenton | B6: Kayne Anderson | C6: 66490000 | D6: 47266 | E6: May 2031 | F6: TTHC | G6: Carve-outs only, plus reserve replenishment | I6: Annual
A7: Panama City Beach | B7: Merchants Bank of Indiana | C7: 49202000 | D7: 47766 | F7: John Thompson and Paul Thrift, each | G7: Carve-outs only | I7: Annual
A8: Ponte Vedra | B8: Trustmark | C8: 50000000 | D8: 47162 | E8: 47527 | F8: TTHC | G8: 50%, then 35%, then 25% | I8: Each 12/31
A9: Port St Lucie | B9: Blackstone / FGL | C9: 44500000 | D9: 46997 | E9: 47727 | F9: TTHC | G9: Carve-outs only | I9: At all times
A10: Sarasota | B10: Stifel | C10: 59900000 | D10: 46385 | E10: None | F10: TTHC | G10: 55%, then 25% at 1.30x | I10: While the loan is in effect
A11: St. Augustine | B11: Simmons | C11: 49200000 | D11: 46748 | E11: 47114 | F11: TTHC | G11: 40%, then 25% at completion | H11: Liquidity excludes the borrower's liquid assets; a miss is an Event of Default | I11: At all times
A12: Venice | B12: UMB | C12: 52250000 | D12: 46519 | E12: 46885 | F12: TTHC | G12: 50% of loan | I12: Annual
A13: Pooler | B13: Fifth Third | C13: 54250000 | D13: 46714 | E13: 47080 | F13: TTHC | G13: Steps down to $13,562,500; starting amount not reviewed | I13: Each fiscal year end
A14: Stockbridge | B14: UMB | C14: 37375630 | D14: 46748 | E14: 47296 | F14: TTHC | G14: 40%, then 25% at completion and 1.20x | I14: At all times; certified annually
A15: Nampa Sundance | B15: Wintrust | C15: 45600000 | D15: 46846 | E15: 47394 | F15: TTHC | G15: 40%, then 25% at 1.20x on 4/30/2027 | H15: No net worth or liquidity covenant | I15: Annual financial statements only
A16: 2022 Fund (Barings) | B16: Barings (2022 Fund) | C16: 548500000 | D16: 46914 | E16: 47644 | F16: TTHC | G16: Carve-outs only | H16: Net worth and liquidity step down after Portfolio DSCR of 1.15x for two straight quarters | I16: At all times; certified each June and December
A17: 2023 Fund (Barings) | B17: Barings (2023 Fund) | D17: 47401 | E17: 48131 | F17: TTHC | G17: Carve-outs only | H17: Net worth and liquidity step down after Portfolio DSCR of 1.15x for two straight quarters | I17: At all times; certified each June and December
A18: Fayetteville Van Asche | B18: Associated / Trustmark | C18: 51000000 | D18: 47280 | E18: 47828 | F18: TTHC | G18: $15.3MM cap | I18: Annual
A19: Gilbert Val Vista | B19: Nationwide | C19: 70226883 | D19: 47233 | E19: 47598 | F19: TTHC | G19: Completion and carve-outs only | I19: Quarterly certificate, due in 45 days
A20: Venetucci | B20: PNC | C20: 63240018 | D20: 47245 | E20: 47794 | F20: TTHC | G20: 40%, then 25% at mini perm | H20: Contingent liabilities no more than 25x unrestricted cash | I20: Semi-annual
A21: Longmont Hover | B21: Stifel | C21: 63744900 | D21: 46923 | E21: 47471 | F21: TTHC | G21: 50%, then 25% at completion and 1.25x | I21: Each year end
A22: Monument Higby | B22: UMB | C22: 58611497 | D22: 47250 | E22: 47799 | F22: TTHC | G22: 40%, then 25% at completion and 1.20x | I22: Annual
A23: Wheat Ridge | B23: BOKF / RCB Bank | C23: 51694640 | D23: 46978 | E23: 47527 | F23: TTHC | G23: 40%, then 30%, then 25% | I23: Quarterly
A24: Buford | B24: BOKF | C24: 56302865 | D24: 47202 | E24: 47751 | F24: TTHC | G24: 25% of loan | I24: Quarterly
A25: Dacula | B25: PNC | C25: 55082113 | D25: 47349 | E25: 47898 | F25: TTHC | G25: 25% of loan | H25: Contingent liabilities no more than 25x unrestricted cash | I25: Semi-annual
A26: Newnan | B26: Comerica | C26: 38496000 | D26: June 2029 | E26: June 2031 | F26: TTHC | G26: 40%, then 25% at completion | I26: Liquidity semi-annual, net worth annual
A27: Fishers Union | B27: First Internet Bank | C27: 78000000 | D27: 47087 | E27: 47634 | F27: TTHC | G27: 40%, then 25% at 1.20x | I27: Each fiscal year end
A28: Westfield 191st | B28: Fifth Third | C28: 56476922 | D28: 47434 | E28: 47799 | F28: TTHC | G28: $16,943,077, then $8,471,538 | I28: Each year end
A29: Overland Park | B29: Simmons | C29: 53870265 | D29: 47269 | E29: 47634 | F29: TTHC | G29: 30% of loan | I29: At all times
A31: Net worth and liquidity minimums are hard dollar amounts in line with TT's typical terms and are not tracked here; only non-standard guarantor terms are noted.

Sheet Forecast
A1: # | B1: Property | C1: Full Name | D1: State | E1: City | F1: Street | G1: Budget Code | H1: Entity | I1: Units | J1: In Aug 2026 Forecast | K1: Jan-27 Occ % | L1: Dec-27 Occ % | M1: 2027 Total Income | N1: 2027 NOI
A2: 1 | B2: Dove Valley | C2: AZ, Phoenix, Dove Valley Rd | D2: AZ | E2: Phoenix | F2: Dove Valley Rd | G2: wdove | H2: TTRES AZ Phoenix 29th Ave Dove Valley Dev LLC | I2: 224 | J2: Yes | K2: 0.9241 | L2: 0.9286 | M2: 4751037 | N2: 2483903
A3: 2 | B3: Spectrum Loop | C3: CO, Colorado Springs, Spectrum Loop | D3: CO | E3: Colorado Springs | F3: Spectrum Loop | G3: wloop | H3: TTRES CO Colorado Springs Spectrum Loop LLC | I3: 276 | J3: Yes | K3: 0.8841 | L3: 0.9312 | M3: 5932626 | N3: 3356960
A4: 3 | B4: Fort Collins Shields | C4: CO, Fort Collins, Shields St | D4: CO | E4: Fort Collins | F4: Shields St | G4: wfcco | H4: TTRES Fort Collins Shields CO LLC | I4: 319 | J4: Yes | K4: 0.93 | L4: 0.945 | M4: 8380804 | N4: 5638593
A5: 4 | B5: Fort Collins Vine | C5: CO, Fort Collins, Vine Dr. | D5: CO | E5: Fort Collins | F5: Vine Dr. | G5: wvine | H5: TTRES CO Fort Collins Vine, LLC | I5: 344 | J5: Yes | K5: 0.8023 | L5: 0.936 | M5: 7857184 | N5: 5070369
A6: 5 | B6: Ellenton | C6: FL, Ellenton, 60th Ave | D6: FL | E6: Ellenton | F6: 60th Ave | G6: welfl | H6: Watermark at Ellenton 60th FL LLC | I6: 320 | J6: Yes | K6: 0.845 | L6: 0.9375 | M6: 6946227 | N6: 3726202
A7: 6 | B7: Panama City Beach | C7: FL, Panama City, Panama City Beach Pkwy | D7: FL | E7: Panama City | F7: Panama City Beach Pkwy | G7: wpcbf | H7: Watermark at PCB FL LLC | I7: 312 | J7: Yes | K7: 0.94 | L7: 0.9375 | M7: 6217086 | N7: 3475011
A8: 7 | B8: Ponte Vedra | C8: FL, Ponte Vedra Beach, Burbank Ave | D8: FL | E8: Ponte Vedra Beach | F8: Burbank Ave | G8: wpvbf | H8: TTRES FL Ponte Vedra Beach LLC | I8: 312 | J8: Yes | K8: 0.6314 | L8: 0.9551 | M8: 6001255 | N8: 3067871
A9: 8 | B9: Port St Lucie | C9: FL, Port St Lucie, 11918 Community Blvd | D9: FL | E9: Port St Lucie | F9: 11918 Community Blvd | G9: wpslf | H9: Watermark at Port St Lucie FL LLC | I9: 214 | J9: Yes | K9: 0.945 | L9: 0.9486 | M9: 5947819 | N9: 2862637
A10: 9 | B10: Sarasota | C10: FL, Sarasota, Fruitville Rd. | D10: FL | E10: Sarasota | F10: Fruitville Rd. | G10: wsfld | H10: TTRES FL Sarasota Apex Rd Development LLC | I10: 257 | J10: Yes | K10: 0.9416 | L10: 0.9416 | M10: 6769948 | N10: 3866275
A11: 10 | B11: St. Augustine | C11: FL, St. Augustine, Outlet Center Dr. | D11: FL | E11: St. Augustine | F11: Outlet Center Dr. | G11: wsaug | H11: TTRes FL St. Augustine Outlet Centre LLC | I11: 324 | J11: Yes | K11: 0.716 | L11: 0.9198 | M11: 5623746 | N11: 2358144
A12: 11 | B12: Venice | C12: FL, Venice, Pinebrook Rd | D12: FL | E12: Venice | F12: Pinebrook Rd | G12: wvenf | H12: Watermark at Venice Pinebrook FL LLC | I12: 244 | J12: Yes | K12: 0.9303 | L12: 0.9303 | M12: 6177110 | N12: 3351793
A13: 12 | B13: Pooler | C13: GA, Pooler, Pooler Pkwy | D13: GA | E13: Pooler | F13: Pooler Pkwy | G13: wpool | H13: TTRES GA Pooler LLC | I13: 360 | J13: Yes | K13: 0.6389 | L13: 0.85 | M13: 5920764 | N13: 2727792
... A15: 14 | B15: Nampa Sundance | C15: ID, Nampa, Sundance Rd. | D15: ID | E15: Nampa | F15: Sundance Rd. | G15: wnpad | H15: TTRES ID Nampa Sundance LLC | I15: 264 | J15: Yes | K15: 0.8598 | L15: 0.9318 | M15: 5511678 | N15: 3177353
A16: 15 | B16: 2022 Fund (Barings) | C16: 2022 Fund (Barings, 9 properties) | I16: =I43 -> 2543 | J16: Yes | K16: =K43 -> 0.94031475 | L16: =L43 -> 0.93904098 | M16: =M43 -> 57796804 | N16: =N43 -> 32302907
A17: 16 | B17: 2023 Fund (Barings) | C17: 2023 Fund (Barings, 8 properties) | I17: =I55 -> 2412 | J17: Yes | K17: =K55 -> 0.79600498 | L17: =L55 -> 0.93948242 | M17: =M55 -> 52176426 | N17: =N55 -> 28605440
A18: 17 | B18: Fayetteville Van Asche | C18: AR, Fayetteville, Van Asche | D18: AR | E18: Fayetteville | F18: Van Asche | G18: wfvar | H18: TTRES AR Fayetteville Van Asche LLC | I18: 324 | J18: No | K18: 0 | L18: 0.2438 | M18: 47144 | N18: -220413
A19: 18 | B19: Gilbert Val Vista | C19: AZ, Gilbert, Germann Val Vista | D19: AZ | E19: Gilbert | F19: Germann Val Vista | G19: wvalv | H19: TTRES AZ Gilbert Germann Val Vista Dev LLC | I19: 300 | J19: No | K19: 0.0733 | L19: 0.6667 | M19: 2255044 | N19: 152599
A20: 19 | B20: Venetucci | C20: CO, Colorado Springs, Venetucci Blvd | D20: CO | E20: Colorado Springs | F20: Venetucci Blvd | G20: wcvco | H20: TTRES CO Colorado Springs Venetucci Blvd LLC | I20: 336 | J20: No | K20: 0.0238 | L20: 0.4725 | M20: 1471588 | N20: 1190312
A21: 20 | B21: Longmont Hover | C21: CO, Longmont, Hover | D21: CO | E21: Longmont | F21: Hover | G21: whovr | H21: TTRES CO Longmont Hover, LLC | I21: 324 | J21: No | K21: 0.4012 | L21: 0.8395 | M21: 4107207 | N21: 1835421
A22: 21 | B22: Monument Higby | C22: CO, Monument, Higby | D22: CO | E22: Monument | F22: Higby | G22: wmhco | H22: TTRES CO Monument Higby LLC | I22: 300 | J22: No | K22: 0.0267 | L22: 0.5325 | M22: 1322278 | N22: 1029818
A23: 22 | B23: Wheat Ridge | C23: CO, Wheat Ridge, Kipling St | D23: CO | E23: Wheat Ridge | F23: Kipling St | G23: wwrco | H23: TTRES CO Wheat Ridge Kipling St LLC | I23: 255 | J23: No | K23: 0.1608 | L23: 0.7686 | M23: 2689627 | N23: 662984
A24: 23 | B24: Buford | C24: GA, Buford, Laurel Crossing | D24: GA | E24: Buford | F24: Laurel Crossing | G24: wbuga | H24: TTRES GA Buford Laurel Crossing LLC | I24: 300 | J24: No | K24: 0 | L24: 0.4533 | M24: 31100 | N24: -249899
A25: 24 | B25: Dacula | C25: GA, Dacula, Harbins Rd | D25: GA | E25: Dacula | F25: Harbins Rd | G25: wdacg | H25: TTRES GA Dacula Harbins Rd Dev LLC | I25: 300 | J25: No | K25: 0 | L25: 0.4067 | M25: 1088088 | N25: 815610
A26: 25 | B26: Newnan | C26: GA, Newnan, Newnan Crossing | D26: GA | E26: Newnan | F26: Newnan Crossing | G26: wncga | H26: TTRES GA Newnan Crossing LLC | I26: 214 | J26: No | K26: 0 | L26: 0.6916 | M26: -385889 | N26: -638157
A27: 26 | B27: Fishers Union | C27: IN, Fishers, Union | D27: IN | E27: Fishers | F27: Union | G27: wunfd | H27: TTRES IN Fishers Union LLC | I27: 251 | J27: No | K27: 0.1912 | L27: 0.8008 | M27: 2902183 | N27: 1077708
A28: 27 | B28: Westfield 191st | C28: IN, Westfield, 191st | D28: IN | E28: Westfield | F28: 191st | G28: wwfin | H28: TTRES IN Westfield 191st LLC | I28: 350 | J28: No | K28: 0 | L28: 0.435 | M28: 1053594 | N28: 777099
A29: 28 | B29: Overland Park | C29: KS, Overland Park, Metcalf | D29: KS | E29: Overland Park | F29: Metcalf | G29: wovpk | H29: TTRES KS Overland Park Metcalf LLC | I29: 303 | J29: No | K29: 0 | L29: 0.4422 | M29: 29237 | N29: -238746
B30: Total | I30: =SUM(I2:I29) -> 12494 | K30: =SUMPRODUCT($I$2:$I$29,K2:K29)/$I$30 -> 0.63347978 | L30: =SUMPRODUCT($I$2:$I$29,L2:L29)/$I$30 -> 0.82565162 | M30: =SUM(M2:M29) -> 213868923 | N30: =SUM(N2:N29) -> 115200993
A32: 2022 Fund detail (Barings, 9 properties)
A33: # | B33: Property | C33: Full Name | D33: State | E33: City | F33: Street | G33: Budget Code | H33: Entity | I33: Units | J33: In Aug 2026 Forecast | K33: Jan-27 Occ % | L33: Dec-27 Occ % | M33: 2027 Total Income | N33: 2027 NOI
A34: 1 | B34: Buckeye Yuma Rd | C34: AZ, Buckeye, Yuma Rd | D34: AZ | E34: Buckeye | F34: Yuma Rd | G34: wbuck | H34: TTRES AZ Buckeye Yuma Rd LLC | I34: 252 | J34: Yes | K34: 0.925 | L34: 0.94 | M34: 4740071 | N34: 2336427
A35: 2 | B35: Fountain Metropolitan Road | C35: CO, Fountain, Metropolitan Road | D35: CO | E35: Fountain | F35: Metropolitan Road | G35: wfoun | H35: TTRES CO Fountain Metropolitan LLC | I35: 336 | J35: Yes | K35: 0.9345 | L35: 0.9345 | M35: 7995627 | N35: 5088218
A36: 3 | B36: Greeley Centerplace Dr | C36: CO, Greeley, Centerplace Dr | D36: CO | E36: Greeley | F36: Centerplace Dr | G36: wgrco | H36: TTRES CO Greeley Centerplace Dr LLC | I36: 336 | J36: Yes | K36: 0.955 | L36: 0.92 | M36: 7200170 | N36: 4481513
A37: 4 | B37: Monument Jackson Creek Pkwy | C37: CO, Monument, Jackson Creek Pkwy | D37: CO | E37: Monument | F37: Jackson Creek Pkwy | G37: wmoco | H37: TTRES CO Monument Jackson Creek, LLC | I37: 264 | J37: Yes | K37: 0.928 | L37: 0.9697 | M37: 6031030 | N37: 3279643
A38: 5 | B38: Daytona Williamson Blvd | C38: FL, Daytona, Williamson Blvd | D38: FL | E38: Daytona | F38: Williamson Blvd | G38: wdwfl | H38: Watermark at Daytona Williamson FL LLC | I38: 300 | J38: Yes | K38: 0.94 | L38: 0.9433 | M38: 6414738 | N38: 3257380
A39: 6 | B39: Ocala 48th Ave | C39: FL, Ocala, 48th Ave | D39: FL | E39: Ocala | F39: 48th Ave | G39: wocfl | H39: TTRES at Ocala 48th FL LLC | I39: 320 | J39: Yes | K39: 0.94 | L39: 0.9438 | M39: 6580083 | N39: 3369190
A40: 7 | B40: Wyoming Wilson Ave | C40: MI, Wyoming, Wilson Ave | D40: MI | E40: Wyoming | F40: Wilson Ave | G40: wwymi | H40: TTRES MI Wyoming Baneberry Ave LLC | I40: 344 | J40: Yes | K40: 0.9506 | L40: 0.9331 | M40: 9371085 | N40: 4739605
A41: 8 | B41: Woodbury Spring Hill Dr | C41: MN, Woodbury, Spring Hill Dr | D41: MN | E41: Woodbury | F41: Spring Hill Dr | G41: wwood | H41: TTRES at Woodbury Springhill MN LLC | I41: 91 | J41: Yes | K41: 0.95 | L41: 0.956 | M41: 3654361 | N41: 2224334
A42: 9 | B42: Raymore Dean Ave | C42: MO, Raymore, Dean Ave | D42: MO | E42: Raymore | F42: Dean Ave | G42: wraym | H42: TTRES MO Raymore Dean Ave LLC | I42: 300 | J42: Yes | K42: 0.94 | L42: 0.93 | M42: 5809639 | N42: 3526597
B43: 2022 Fund total | I43: =SUM(I34:I42) -> 2543 | K43: =SUMPRODUCT($I$34:$I$42,K34:K42)/$I$43 -> 0.94031475 | L43: =SUMPRODUCT($I$34:$I$42,L34:L42)/$I$43 -> 0.93904098 | M43: =SUM(M34:M42) -> 57796804 | N43: =SUM(N34:N42) -> 32302907
A45: 2023 Fund detail (Barings, 8 properties)
A46: # | B46: Property | C46: Full Name | D46: State | E46: City | F46: Street | G46: Budget Code | H46: Entity | I46: Units | J46: In Aug 2026 Forecast | K46: Jan-27 Occ % | L46: Dec-27 Occ % | M46: 2027 Total Income | N46: 2027 NOI
A47: 1 | B47: San Tan Valley Gary Rd | C47: AZ, San Tan Valley, Gary Rd | D47: AZ | E47: San Tan Valley | F47: Gary Rd | G47: wstnd | H47: TTRES AZ San Tan Valley Hunt Dev LLC | I47: 308 | J47: Yes | K47: 0.7305 | L47: 0.9188 | M47: 5445971 | N47: 2956646
A48: 2 | B48: Bradenton El Conquistador Pkwy | C48: FL, Bradenton, El Conquistador Pkwy | D48: FL | E48: Bradenton | F48: El Conquistador Pkwy | G48: wbrtn | H48: TTRES FL Bradenton EL Conquistador LLC | I48: 280 | J48: Yes | K48: 0.9071 | L48: 0.9536 | M48: 7218420 | N48: 3895108
A49: 3 | B49: Lady Lake SE 135th | C49: FL, Lady Lake, SE 135th | D49: FL | E49: Lady Lake | F49: SE 135th | G49: wlady | H49: TTRES FL Lady Lake 136th Ave Dev LLC | I49: 300 | J49: Yes | K49: 0.8867 | L49: 0.94 | M49: 5868156 | N49: 3266504
A50: 4 | B50: North Port Sumter Blvd | C50: FL, North Port, Sumter Blvd | D50: FL | E50: North Port | F50: Sumter Blvd | G50: wnpfl | H50: TTRES FL North Port Sumter LLC | I50: 268 | J50: Yes | K50: 0.6604 | L50: 0.9366 | M50: 5599113 | N50: 2689190
A51: 5 | B51: Pensacola W Nine Mile Rd | C51: FL, Pensacola, W Nine Mile Rd | D51: FL | E51: Pensacola | F51: W Nine Mile Rd | G51: wpn9m | H51: TTRES FL Pensacola 9 Mile, LLC | I51: 324 | J51: Yes | K51: 0.8549 | L51: 0.9475 | M51: 6737088 | N51: 3789334
A52: 6 | B52: Rockledge Fiske Blvd | C52: FL, Rockledge, Fiske Blvd | D52: FL | E52: Rockledge | F52: Fiske Blvd | G52: wrckd | H52: TTRES FL Rockledge Fiske Trail Dev LLC | I52: 380 | J52: Yes | K52: 0.75 | L52: 0.9316 | M52: 8722689 | N52: 5050024
A53: 7 | B53: Vero Beach 11th Dr. | C53: FL, Vero Beach, 11th Dr. | D53: FL | E53: Vero Beach | F53: 11th Dr. | G53: wvero | H53: TTRES FL Vero Beach 11th LLC | I53: 276 | J53: Yes | K53: 0.721 | L53: 0.9457 | M53: 6484210 | N53: 3766100
A54: 8 | B54: Union City Derrick | C54: GA, Union City, Derrick | D54: GA | E54: Union City | F54: Derrick | G54: wucga | H54: TTRES GA Union City Derrick, LLC | I54: 276 | J54: Yes | K54: 0.8587 | L54: 0.9457 | M54: 6100779 | N54: 3192534
B55: 2023 Fund total | I55: =SUM(I47:I54) -> 2412 | K55: =SUMPRODUCT($I$47:$I$54,K47:K54)/$I$55 -> 0.79600498 | L55: =SUMPRODUCT($I$47:$I$54,L47:L54)/$I$55 -> 0.93948242 | M55: =SUM(M47:M54) -> 52176426 | N55: =SUM(N47:N54) -> 28605440
A57: Source: 2027 Budgets - Forecast Format.xlsx. Fund detail below supports the portfolio totals; do not add it again. Expand grouped columns for full property identifiers.

Sheet Property Reference
A1: Property Covenant Reference
A2: Property-level descriptions and future test start dates.
A3: =HYPERLINK("#'Summary'!A1","Back to Summary") -> Back to Summary
A4: # | B4: Property | C4: Lender | D4: Initial Maturity | E4: Key Tests | F4: First New Test | G4: New 2027 Tests | H4: Ongoing / Event-driven in 2027 | I4: First new test starting after 2027 | J4: Non-standard Guarantor Terms
A5: 1 | B5: =HYPERLINK("#'Covenant Tests'!A"&(MATCH("Dove Valley",'Covenant Tests'!$A$2:$A$107,0)+1),"Dove Valley") -> Dove Valley | C5: Nationwide | D5: 46692 | E5: Cash sweep; net cash flow 105% of interest and LTV 65% to extend at 11/1/2027 | F5: =IF(COUNTIFS('2027 Calendar'!$B:$B,$B5,'2027 Calendar'!$D:$D,"Test")=0,"None",_xlfn.MINIFS('2027 Calendar'!$A:$A,'2027 Calendar'!$B:$B,$B5,'2027 Calendar'!$D:$D,"Test")) -> 46692 | G5: =COUNTIFS('2027 Calendar'!$B:$B,$B5,'2027 Calendar'!$D:$D,"Test") -> 1 | H5: Cash sweep and distribution block (monthly); Interest reserve top-up (On lender notice) | I5: =IF(COUNTIFS('Covenant Tests'!$A:$A,$B5,'Covenant Tests'!$F:$F,">"&DATE(2027,12,31))=0,"",_xlfn.MINIFS('Covenant Tests'!$F:$F,'Covenant Tests'!$A:$A,$B5,'Covenant Tests'!$F:$F,">"&DATE(2027,12,31)))
A6: 2 | B6: =HYPERLINK("#'Covenant Tests'!A"&(MATCH("Spectrum Loop",'Covenant Tests'!$A$2:$A$107,0)+1),"Spectrum Loop") -> Spectrum Loop | C6: Nationwide | D6: 47014 | E6: Cash sweep; net cash flow 105% of interest and LTV 66% to extend in 2028 | F6: =IF(COUNTIFS('2027 Calendar'!$B:$B,$B6,'2027 Calendar'!$D:$D,"Test")=0,"None",_xlfn.MINIFS('2027 Calendar'!$A:$A,'2027 Calendar'!$B:$B,$B6,'2027 Calendar'!$D:$D,"Test")) -> None | G6: =COUNTIFS('2027 Calendar'!$B:$B,$B6,'2027 Calendar'!$D:$D,"Test") -> 0 | H6: Cash sweep and distribution block (monthly); Interest reserve top-up (On lender notice) | I6: =IF(COUNTIFS('Covenant Tests'!$A:$A,$B6,'Covenant Tests'!$F:$F,">"&DATE(2027,12,31))=0,"",_xlfn.MINIFS('Covenant Tests'!$F:$F,'Covenant Tests'!$A:$A,$B6,'Covenant Tests'!$F:$F,">"&DATE(2027,12,31))) -> 47014
A7: 3 | B7: =HYPERLINK("#'Covenant Tests'!A"&(MATCH("Fort Collins Shields",'Covenant Tests'!$A$2:$A$107,0)+1),"Fort Collins Shields") -> Fort Collins Shields | C7: Starwood | D7: 46974 | E7: Cash trap at Debt Yield under 6.50% from 8/9/2027; 7.00% to extend | F7: =IF(COUNTIFS('2027 Calendar'!$B:$B,$B7,'2027 Calendar'!$D:$D,"Test")=0,"None",_xlfn.MINIFS('2027 Calendar'!$A:$A,'2027 Calendar'!$B:$B,$B7,'2027 Calendar'!$D:$D,"Test")) -> 46608 | G7: =COUNTIFS('2027 Calendar'!$B:$B,$B7,'2027 Calendar'!$D:$D,"Test") -> 1 | H7: None | I7: =IF(COUNTIFS('Covenant Tests'!$A:$A,$B7,'Covenant Tests'!$F:$F,">"&DATE(2027,12,31))=0,"",_xlfn.MINIFS('Covenant Tests'!$F:$F,'Covenant Tests'!$A:$A,$B7,'Covenant Tests'!$F:$F,">"&DATE(2027,12,31))) -> 46974
A8: 4 | B8: =HYPERLINK("#'Covenant Tests'!A"&(MATCH("Fort Collins Vine",'Covenant Tests'!$A$2:$A$107,0)+1),"Fort Collins Vine") -> Fort Collins Vine | C8: Western-Southern | D8: 47309 | E8: Pay down to Debt Yield 9.75% at 6/30/2028 unless NOI reaches $6,775,000 | F8: =IF(COUNTIFS('2027 Calendar'!$B:$B,$B8,'2027 Calendar'!$D:$D,"Test")=0,"None",_xlfn.MINIFS('2027 Calendar'!$A:$A,'2027 Calendar'!$B:$B,$B8,'2027 Calendar'!$D:$D,"Test")) -> None | G8: =COUNTIFS('2027 Calendar'!$B:$B,$B8,'2027 Calendar'!$D:$D,"Test") -> 0 | H8: Stabilization: NOI (until met, by June 2028) | I8: =IF(COUNTIFS('Covenant Tests'!$A:$A,$B8,'Covenant Tests'!$F:$F,">"&DATE(2027,12,31))=0,"",_xlfn.MINIFS('Covenant Tests'!$F:$F,'Covenant Tests'!$A:$A,$B8,'Covenant Tests'!$F:$F,">"&DATE(2027,12,31))) -> 46934 | J8: Note 5.6 paydown liability capped at $10,250,000
A9: 5 | B9: =HYPERLINK("#'Covenant Tests'!A"&(MATCH("Ellenton",'Covenant Tests'!$A$2:$A$107,0)+1),"Ellenton") -> Ellenton | C9: Kayne Anderson | D9: 47266 | E9: Debt Yield 6.00% and Implied DSCR 1.00x (cash trap) | F9: =IF(COUNTIFS('2027 Calendar'!$B:$B,$B9,'2027 Calendar'!$D:$D,"Test")=0,"None",_xlfn.MINIFS('2027 Calendar'!$A:$A,'2027 Calendar'!$B:$B,$B9,'2027 Calendar'!$D:$D,"Test")) -> 46660 | G9: =COUNTIFS('2027 Calendar'!$B:$B,$B9,'2027 Calendar'!$D:$D,"Test") -> 2 | H9: Interest reserve replenishment (On lender notice) | I9: =IF(COUNTIFS('Covenant Tests'!$A:$A,$B9,'Covenant Tests'!$F:$F,">"&DATE(2027,12,31))=0,"",_xlfn.MINIFS('Covenant Tests'!$F:$F,'Covenant Tests'!$A:$A,$B9,'Covenant Tests'!$F:$F,">"&DATE(2027,12,31))) -> 47266
A10: 6 | B10: =HYPERLINK("#'Covenant Tests'!A"&(MATCH("Panama City Beach",'Covenant Tests'!$A$2:$A$107,0)+1),"Panama City Beach") -> Panama City Beach | C10: Merchants Bank of Indiana | D10: 47766 | E10: Escrow release at DSCR 1.20x and $509,914 monthly rent | F10: =IF(COUNTIFS('2027 Calendar'!$B:$B,$B10,'2027 Calendar'!$D:$D,"Test")=0,"None",_xlfn.MINIFS('2027 Calendar'!$A:$A,'2027 Calendar'!$B:$B,$B10,'2027 Calendar'!$D:$D,"Test")) -> None | G10: =COUNTIFS('2027 Calendar'!$B:$B,$B10,'2027 Calendar'!$D:$D,"Test") -> 0 | H10: Rent collection escrow release (until released) | I10: =IF(COUNTIFS('Covenant Tests'!$A:$A,$B10,'Covenant Tests'!$F:$F,">"&DATE(2027,12,31))=0,"",_xlfn.MINIFS('Covenant Tests'!$F:$F,'Covenant Tests'!$A:$A,$B10,'Covenant Tests'!$F:$F,">"&DATE(2027,12,31))) | J10: Guarantor: John Thompson and Paul Thrift, each
A11: 7 | B11: =HYPERLINK("#'Covenant Tests'!A"&(MATCH("Ponte Vedra",'Covenant Tests'!$A$2:$A$107,0)+1),"Ponte Vedra") -> Ponte Vedra | C11: Trustmark | D11: 47162 | E11: DSCR 1.00x from 8/31/2028; 1.25x and LTV 61% to extend | F11: =IF(COUNTIFS('2027 Calendar'!$B:$B,$B11,'2027 Calendar'!$D:$D,"Test")=0,"None",_xlfn.MINIFS('2027 Calendar'!$A:$A,'2027 Calendar'!$B:$B,$B11,'2027 Calendar'!$D:$D,"Test")) -> None | G11: =COUNTIFS('2027 Calendar'!$B:$B,$B11,'2027 Calendar'!$D:$D,"Test") -> 0 | H11: None | I11: =IF(COUNTIFS('Covenant Tests'!$A:$A,$B11,'Covenant Tests'!$F:$F,">"&DATE(2027,12,31))=0,"",_xlfn.MINIFS('Covenant Tests'!$F:$F,'Covenant Tests'!$A:$A,$B11,'Covenant Tests'!$F:$F,">"&DATE(2027,12,31))) -> 46996
A12: 8 | B12: =HYPERLINK("#'Covenant Tests'!A"&(MATCH("Port St Lucie",'Covenant Tests'!$A$2:$A$107,0)+1),"Port St Lucie") -> Port St Lucie | C12: Blackstone / FGL | D12: 46997 | E12: Cash trap on until NOI $3,000,000; Debt Yield 8.00% and DSCR 1.25x from 3/31/2027 | F12: =IF(COUNTIFS('2027 Calendar'!$B:$B,$B12,'2027 Calendar'!$D:$D,"Test")=0,"None",_xlfn.MINIFS('2027 Calendar'!$A:$A,'2027 Calendar'!$B:$B,$B12,'2027 Calendar'!$D:$D,"Test")) -> 46477 | G12: =COUNTIFS('2027 Calendar'!$B:$B,$B12,'2027 Calendar'!$D:$D,"Test") -> 1 | H12: Cash trap since closing (until cured); Cash Collateral Reserve release (until released); Additional Cash Collateral release (until released) | I12: =IF(COUNTIFS('Covenant Tests'!$A:$A,$B12,'Covenant Tests'!$F:$F,">"&DATE(2027,12,31))=0,"",_xlfn.MINIFS('Covenant Tests'!$F:$F,'Covenant Tests'!$A:$A,$B12,'Covenant Tests'!$F:$F,">"&DATE(2027,12,31))) -> 46997
A13: 9 | B13: =HYPERLINK("#'Covenant Tests'!A"&(MATCH("Sarasota",'Covenant Tests'!$A$2:$A$107,0)+1),"Sarasota") -> Sarasota | C13: Stifel | D13: 46385 | E13: Hard maturity 12/29/2026; the 1.20x covenant never tests | F13: =IF(COUNTIFS('2027 Calendar'!$B:$B,$B13,'2027 Calendar'!$D:$D,"Test")=0,"None",_xlfn.MINIFS('2027 Calendar'!$A:$A,'2027 Calendar'!$B:$B,$B13,'2027 Calendar'!$D:$D,"Test")) -> None | G13: =COUNTIFS('2027 Calendar'!$B:$B,$B13,'2027 Calendar'!$D:$D,"Test") -> 0 | H13: None | I13: =IF(COUNTIFS('Covenant Tests'!$A:$A,$B13,'Covenant Tests'!$F:$F,">"&DATE(2027,12,31))=0,"",_xlfn.MINIFS('Covenant Tests'!$F:$F,'Covenant Tests'!$A:$A,$B13,'Covenant Tests'!$F:$F,">"&DATE(2027,12,31)))
A14: 10 | B14: =HYPERLINK("#'Covenant Tests'!A"&(MATCH("St. Augustine",'Covenant Tests'!$A$2:$A$107,0)+1),"St. Augustine") -> St. Augustine | C14: Simmons | D14: 46748 | E14: DSCR 1.35x quarterly; 1.25x and LTV 55% to extend | F14: =IF(COUNTIFS('2027 Calendar'!$B:$B,$B14,'2027 Calendar'!$D:$D,"Test")=0,"None",_xlfn.MINIFS('2027 Calendar'!$A:$A,'2027 Calendar'!$B:$B,$B14,'2027 Calendar'!$D:$D,"Test")) -> 46748 | G14: =COUNTIFS('2027 Calendar'!$B:$B,$B14,'2027 Calendar'!$D:$D,"Test") -> 1 | H14: Cash trap before stabilization (until Initial Stabilization); Cash trap after stabilization (After stabilization); Loan to cost (At all times); Distribution block (At all times) | I14: =IF(COUNTIFS('Covenant Tests'!$A:$A,$B14,'Covenant Tests'!$F:$F,">"&DATE(2027,12,31))=0,"",_xlfn.MINIFS('Covenant Tests'!$F:$F,'Covenant Tests'!$A:$A,$B14,'Covenant Tests'!$F:$F,">"&DATE(2027,12,31))) | J14: Liquidity excludes the borrower's liquid assets; a miss is an Event of Default
A15: 11 | B15: =HYPERLINK("#'Covenant Tests'!A"&(MATCH("Venice",'Covenant Tests'!$A$2:$A$107,0)+1),"Venice") -> Venice | C15: UMB | D15: 46519 | E15: DSCR 1.10x; occupancy 87.5% | F15: =IF(COUNTIFS('2027 Calendar'!$B:$B,$B15,'2027 Calendar'!$D:$D,"Test")=0,"None",_xlfn.MINIFS('2027 Calendar'!$A:$A,'2027 Calendar'!$B:$B,$B15,'2027 Calendar'!$D:$D,"Test")) -> 46507 | G15: =COUNTIFS('2027 Calendar'!$B:$B,$B15,'2027 Calendar'!$D:$D,"Test") -> 1 | H15: LTV Threshold (On appraisal); Reserve Account minimum (at all times) | I15: =IF(COUNTIFS('Covenant Tests'!$A:$A,$B15,'Covenant Tests'!$F:$F,">"&DATE(2027,12,31))=0,"",_xlfn.MINIFS('Covenant Tests'!$F:$F,'Covenant Tests'!$A:$A,$B15,'Covenant Tests'!$F:$F,">"&DATE(2027,12,31)))
A16: 12 | B16: =HYPERLINK("#'Covenant Tests'!A"&(MATCH("Pooler",'Covenant Tests'!$A$2:$A$107,0)+1),"Pooler") -> Pooler | C16: Fifth Third | D16: 46714 | E16: DSCR 1.00x from 5/23/2027, 1.20x from 11/23/2027; 1.20x and LTV 60% to extend | F16: =IF(COUNTIFS('2027 Calendar'!$B:$B,$B16,'2027 Calendar'!$D:$D,"Test")=0,"None",_xlfn.MINIFS('2027 Calendar'!$A:$A,'2027 Calendar'!$B:$B,$B16,'2027 Calendar'!$D:$D,"Test")) -> 46530 | G16: =COUNTIFS('2027 Calendar'!$B:$B,$B16,'2027 Calendar'!$D:$D,"Test") -> 2 | H16: Distribution test: DSCR (Before distributions) | I16: =IF(COUNTIFS('Covenant Tests'!$A:$A,$B16,'Covenant Tests'!$F:$F,">"&DATE(2027,12,31))=0,"",_xlfn.MINIFS('Covenant Tests'!$F:$F,'Covenant Tests'!$A:$A,$B16,'Covenant Tests'!$F:$F,">"&DATE(2027,12,31)))
A17: 13 | B17: =HYPERLINK("#'Covenant Tests'!A"&(MATCH("Stockbridge",'Covenant Tests'!$A$2:$A$107,0)+1),"Stockbridge") -> Stockbridge | C17: UMB | D17: 46748 | E17: Occupancy 50% then 80%; DSCR 1.15x at 12/27/2027 and to extend; LTV 60% | F17: =IF(COUNTIFS('2027 Calendar'!$B:$B,$B17,'2027 Calendar'!$D:$D,"Test")=0,"None",_xlfn.MINIFS('2027 Calendar'!$A:$A,'2027 Calendar'!$B:$B,$B17,'2027 Calendar'!$D:$D,"Test")) -> 46565 | G17: =COUNTIFS('2027 Calendar'!$B:$B,$B17,'2027 Calendar'!$D:$D,"Test") -> 4 | H17: LTV Threshold (On appraisal) | I17: =IF(COUNTIFS('Covenant Tests'!$A:$A,$B17,'Covenant Tests'!$F:$F,">"&DATE(2027,12,31))=0,"",_xlfn.MINIFS('Covenant Tests'!$F:$F,'Covenant Tests'!$A:$A,$B17,'Covenant Tests'!$F:$F,">"&DATE(2027,12,31)))
A18: 14 | B18: =HYPERLINK("#'Covenant Tests'!A"&(MATCH("Nampa Sundance",'Covenant Tests'!$A$2:$A$107,0)+1),"Nampa Sundance") -> Nampa Sundance | C18: Wintrust | D18: 46846 | E18: DSCR 1.00x at 4/30/2027, then 1.20x; 1.20x to extend | F18: =IF(COUNTIFS('2027 Calendar'!$B:$B,$B18,'2027 Calendar'!$D:$D,"Test")=0,"None",_xlfn.MINIFS('2027 Calendar'!$A:$A,'2027 Calendar'!$B:$B,$B18,'2027 Calendar'!$D:$D,"Test")) -> 46507 | G18: =COUNTIFS('2027 Calendar'!$B:$B,$B18,'2027 Calendar'!$D:$D,"Test") -> 1 | H18: IRM Reserve (At all times); Reappraisal: LTV (On appraisal) | I18: =IF(COUNTIFS('Covenant Tests'!$A:$A,$B18,'Covenant Tests'!$F:$F,">"&DATE(2027,12,31))=0,"",_xlfn.MINIFS('Covenant Tests'!$F:$F,'Covenant Tests'!$A:$A,$B18,'Covenant Tests'!$F:$F,">"&DATE(2027,12,31))) -> 46783 | J18: No net worth or liquidity covenant; annual financial statements only
A19: 15 | B19: =HYPERLINK("#'Covenant Tests'!A"&(MATCH("2022 Fund (Barings)",'Covenant Tests'!$A$2:$A$107,0)+1),"2022 Fund (Barings)") -> 2022 Fund (Barings) | C19: Barings (2022 Fund) | D19: 46914 | E19: Cash trap at Portfolio DSCR under 1.05x; Debt Yield 7.50% to extend | F19: =IF(COUNTIFS('2027 Calendar'!$B:$B,$B19,'2027 Calendar'!$D:$D,"Test")=0,"None",_xlfn.MINIFS('2027 Calendar'!$A:$A,'2027 Calendar'!$B:$B,$B19,'2027 Calendar'!$D:$D,"Test")) -> None | G19: =COUNTIFS('2027 Calendar'!$B:$B,$B19,'2027 Calendar'!$D:$D,"Test") -> 0 | H19: Cash trap: Portfolio DSCR (any time after 5/31/2026) | I19: =IF(COUNTIFS('Covenant Tests'!$A:$A,$B19,'Covenant Tests'!$F:$F,">"&DATE(2027,12,31))=0,"",_xlfn.MINIFS('Covenant Tests'!$F:$F,'Covenant Tests'!$A:$A,$B19,'Covenant Tests'!$F:$F,">"&DATE(2027,12,31))) -> 46914 | J19: Net worth and liquidity step down after Portfolio DSCR of 1.15x for two straight quarters
A20: 16 | B20: =HYPERLINK("#'Covenant Tests'!A"&(MATCH("2023 Fund (Barings)",'Covenant Tests'!$A$2:$A$107,0)+1),"2023 Fund (Barings)") -> 2023 Fund (Barings) | C20: Barings (2023 Fund) | D20: 47401 | E20: Cash trap at Portfolio DSCR under 1.05x after 4/10/2028; Debt Yield 7.50% to extend | F20: =IF(COUNTIFS('2027 Calendar'!$B:$B,$B20,'2027 Calendar'!$D:$D,"Test")=0,"None",_xlfn.MINIFS('2027 Calendar'!$A:$A,'2027 Calendar'!$B:$B,$B20,'2027 Calendar'!$D:$D,"Test")) -> None | G20: =COUNTIFS('2027 Calendar'!$B:$B,$B20,'2027 Calendar'!$D:$D,"Test") -> 0 | H20: None | I20: =IF(COUNTIFS('Covenant Tests'!$A:$A,$B20,'Covenant Tests'!$F:$F,">"&DATE(2027,12,31))=0,"",_xlfn.MINIFS('Covenant Tests'!$F:$F,'Covenant Tests'!$A:$A,$B20,'Covenant Tests'!$F:$F,">"&DATE(2027,12,31))) -> 46853 | J20: Net worth and liquidity step down after Portfolio DSCR of 1.15x for two straight quarters
A21: 17 | B21: =HYPERLINK("#'Covenant Tests'!A"&(MATCH("Fayetteville Van Asche",'Covenant Tests'!$A$2:$A$107,0)+1),"Fayetteville Van Asche") -> Fayetteville Van Asche | C21: Associated / Trustmark | D21: 47280 | E21: DSCR 1.20x to extend and annually after | F21: =IF(COUNTIFS('2027 Calendar'!$B:$B,$B21,'2027 Calendar'!$D:$D,"Test")=0,"None",_xlfn.MINIFS('2027 Calendar'!$A:$A,'2027 Calendar'!$B:$B,$B21,'2027 Calendar'!$D:$D,"Test")) -> None | G21: =COUNTIFS('2027 Calendar'!$B:$B,$B21,'2027 Calendar'!$D:$D,"Test") -> 0 | H21: None | I21: =IF(COUNTIFS('Covenant Tests'!$A:$A,$B21,'Covenant Tests'!$F:$F,">"&DATE(2027,12,31))=0,"",_xlfn.MINIFS('Covenant Tests'!$F:$F,'Covenant Tests'!$A:$A,$B21,'Covenant Tests'!$F:$F,">"&DATE(2027,12,31))) -> 47280
A22: 18 | B22: =HYPERLINK("#'Covenant Tests'!A"&(MATCH("Gilbert Val Vista",'Covenant Tests'!$A$2:$A$107,0)+1),"Gilbert Val Vista") -> Gilbert Val Vista | C22: Nationwide | D22: 47233 | E22: Cash sweep; net cash flow 105% of interest and LTV 65% to extend in 2029 | F22: =IF(COUNTIFS('2027 Calendar'!$B:$B,$B22,'2027 Calendar'!$D:$D,"Test")=0,"None",_xlfn.MINIFS('2027 Calendar'!$A:$A,'2027 Calendar'!$B:$B,$B22,'2027 Calendar'!$D:$D,"Test")) -> None | G22: =COUNTIFS('2027 Calendar'!$B:$B,$B22,'2027 Calendar'!$D:$D,"Test") -> 0 | H22: Cash sweep and distribution block (monthly); Interest reserve top-up (On lender notice) | I22: =IF(COUNTIFS('Covenant Tests'!$A:$A,$B22,'Covenant Tests'!$F:$F,">"&DATE(2027,12,31))=0,"",_xlfn.MINIFS('Covenant Tests'!$F:$F,'Covenant Tests'!$A:$A,$B22,'Covenant Tests'!$F:$F,">"&DATE(2027,12,31))) -> 47233
A23: 19 | B23: =HYPERLINK("#'Covenant Tests'!A"&(MATCH("Venetucci",'Covenant Tests'!$A$2:$A$107,0)+1),"Venetucci") -> Venetucci | C23: PNC | D23: 47245 | E23: DSCR 1.20x to convert, 1.25x after; LTV 60% | F23: =IF(COUNTIFS('2027 Calendar'!$B:$B,$B23,'2027 Calendar'!$D:$D,"Test")=0,"None",_xlfn.MINIFS('2027 Calendar'!$A:$A,'2027 Calendar'!$B:$B,$B23,'2027 Calendar'!$D:$D,"Test")) -> None | G23: =COUNTIFS('2027 Calendar'!$B:$B,$B23,'2027 Calendar'!$D:$D,"Test") -> 0 | H23: None | I23: =IF(COUNTIFS('Covenant Tests'!$A:$A,$B23,'Covenant Tests'!$F:$F,">"&DATE(2027,12,31))=0,"",_xlfn.MINIFS('Covenant Tests'!$F:$F,'Covenant Tests'!$A:$A,$B23,'Covenant Tests'!$F:$F,">"&DATE(2027,12,31))) -> 47245 | J23: Contingent liabilities no more than 25x unrestricted cash
A24: 20 | B24: =HYPERLINK("#'Covenant Tests'!A"&(MATCH("Longmont Hover",'Covenant Tests'!$A$2:$A$107,0)+1),"Longmont Hover") -> Longmont Hover | C24: Stifel | D24: 46923 | E24: DSCR 1.10x | F24: =IF(COUNTIFS('2027 Calendar'!$B:$B,$B24,'2027 Calendar'!$D:$D,"Test")=0,"None",_xlfn.MINIFS('2027 Calendar'!$A:$A,'2027 Calendar'!$B:$B,$B24,'2027 Calendar'!$D:$D,"Test")) -> 46752 | G24: =COUNTIFS('2027 Calendar'!$B:$B,$B24,'2027 Calendar'!$D:$D,"Test") -> 1 | H24: None | I24: =IF(COUNTIFS('Covenant Tests'!$A:$A,$B24,'Covenant Tests'!$F:$F,">"&DATE(2027,12,31))=0,"",_xlfn.MINIFS('Covenant Tests'!$F:$F,'Covenant Tests'!$A:$A,$B24,'Covenant Tests'!$F:$F,">"&DATE(2027,12,31))) -> 46904
A25: 21 | B25: =HYPERLINK("#'Covenant Tests'!A"&(MATCH("Monument Higby",'Covenant Tests'!$A$2:$A$107,0)+1),"Monument Higby") -> Monument Higby | C25: UMB | D25: 47250 | E25: DSCR 1.20x; LTV 60% | F25: =IF(COUNTIFS('2027 Calendar'!$B:$B,$B25,'2027 Calendar'!$D:$D,"Test")=0,"None",_xlfn.MINIFS('2027 Calendar'!$A:$A,'2027 Calendar'!$B:$B,$B25,'2027 Calendar'!$D:$D,"Test")) -> None | G25: =COUNTIFS('2027 Calendar'!$B:$B,$B25,'2027 Calendar'!$D:$D,"Test") -> 0 | H25: None | I25: =IF(COUNTIFS('Covenant Tests'!$A:$A,$B25,'Covenant Tests'!$F:$F,">"&DATE(2027,12,31))=0,"",_xlfn.MINIFS('Covenant Tests'!$F:$F,'Covenant Tests'!$A:$A,$B25,'Covenant Tests'!$F:$F,">"&DATE(2027,12,31))) -> 47238
A26: 22 | B26: =HYPERLINK("#'Covenant Tests'!A"&(MATCH("Wheat Ridge",'Covenant Tests'!$A$2:$A$107,0)+1),"Wheat Ridge") -> Wheat Ridge | C26: BOKF / RCB Bank | D26: 46978 | E26: DSCR 1.15x to extend, 1.25x after; LTV 60% | F26: =IF(COUNTIFS('2027 Calendar'!$B:$B,$B26,'2027 Calendar'!$D:$D,"Test")=0,"None",_xlfn.MINIFS('2027 Calendar'!$A:$A,'2027 Calendar'!$B:$B,$B26,'2027 Calendar'!$D:$D,"Test")) -> None | G26: =COUNTIFS('2027 Calendar'!$B:$B,$B26,'2027 Calendar'!$D:$D,"Test") -> 0 | H26: None | I26: =IF(COUNTIFS('Covenant Tests'!$A:$A,$B26,'Covenant Tests'!$F:$F,">"&DATE(2027,12,31))=0,"",_xlfn.MINIFS('Covenant Tests'!$F:$F,'Covenant Tests'!$A:$A,$B26,'Covenant Tests'!$F:$F,">"&DATE(2027,12,31))) -> 46978
A27: 23 | B27: =HYPERLINK("#'Covenant Tests'!A"&(MATCH("Buford",'Covenant Tests'!$A$2:$A$107,0)+1),"Buford") -> Buford | C27: BOKF | D27: 47202 | E27: DSCR 1.15x to extend, 1.25x after; LTV 60% | F27: =IF(COUNTIFS('2027 Calendar'!$B:$B,$B27,'2027 Calendar'!$D:$D,"Test")=0,"None",_xlfn.MINIFS('2027 Calendar'!$A:$A,'2027 Calendar'!$B:$B,$B27,'2027 Calendar'!$D:$D,"Test")) -> None | G27: =COUNTIFS('2027 Calendar'!$B:$B,$B27,'2027 Calendar'!$D:$D,"Test") -> 0 | H27: None | I27: =IF(COUNTIFS('Covenant Tests'!$A:$A,$B27,'Covenant Tests'!$F:$F,">"&DATE(2027,12,31))=0,"",_xlfn.MINIFS('Covenant Tests'!$F:$F,'Covenant Tests'!$A:$A,$B27,'Covenant Tests'!$F:$F,">"&DATE(2027,12,31))) -> 47202
A28: 24 | B28: =HYPERLINK("#'Covenant Tests'!A"&(MATCH("Dacula",'Covenant Tests'!$A$2:$A$107,0)+1),"Dacula") -> Dacula | C28: PNC | D28: 47349 | E28: DSCR 1.20x to convert and after; LTV 60% | F28: =IF(COUNTIFS('2027 Calendar'!$B:$B,$B28,'2027 Calendar'!$D:$D,"Test")=0,"None",_xlfn.MINIFS('2027 Calendar'!$A:$A,'2027 Calendar'!$B:$B,$B28,'2027 Calendar'!$D:$D,"Test")) -> None | G28: =COUNTIFS('2027 Calendar'!$B:$B,$B28,'2027 Calendar'!$D:$D,"Test") -> 0 | H28: None | I28: =IF(COUNTIFS('Covenant Tests'!$A:$A,$B28,'Covenant Tests'!$F:$F,">"&DATE(2027,12,31))=0,"",_xlfn.MINIFS('Covenant Tests'!$F:$F,'Covenant Tests'!$A:$A,$B28,'Covenant Tests'!$F:$F,">"&DATE(2027,12,31))) -> 47349 | J28: Contingent liabilities no more than 25x unrestricted cash
A29: 25 | B29: =HYPERLINK("#'Covenant Tests'!A"&(MATCH("Newnan",'Covenant Tests'!$A$2:$A$107,0)+1),"Newnan") -> Newnan | C29: Comerica | D29: June 2029 | E29: Interest reserve deposit if IO DSCR under 1.00x; DSCR 1.10x to extend | F29: =IF(COUNTIFS('2027 Calendar'!$B:$B,$B29,'2027 Calendar'!$D:$D,"Test")=0,"None",_xlfn.MINIFS('2027 Calendar'!$A:$A,'2027 Calendar'!$B:$B,$B29,'2027 Calendar'!$D:$D,"Test")) -> None | G29: =COUNTIFS('2027 Calendar'!$B:$B,$B29,'2027 Calendar'!$D:$D,"Test") -> 0 | H29: Interest reserve shortfall (any time) | I29: =IF(COUNTIFS('Covenant Tests'!$A:$A,$B29,'Covenant Tests'!$F:$F,">"&DATE(2027,12,31))=0,"",_xlfn.MINIFS('Covenant Tests'!$F:$F,'Covenant Tests'!$A:$A,$B29,'Covenant Tests'!$F:$F,">"&DATE(2027,12,31)))
A30: 26 | B30: =HYPERLINK("#'Covenant Tests'!A"&(MATCH("Fishers Union",'Covenant Tests'!$A$2:$A$107,0)+1),"Fishers Union") -> Fishers Union | C30: First Internet Bank | D30: 47087 | E30: DSCR 1.15x to extend, 1.20x after | F30: =IF(COUNTIFS('2027 Calendar'!$B:$B,$B30,'2027 Calendar'!$D:$D,"Test")=0,"None",_xlfn.MINIFS('2027 Calendar'!$A:$A,'2027 Calendar'!$B:$B,$B30,'2027 Calendar'!$D:$D,"Test")) -> None | G30: =COUNTIFS('2027 Calendar'!$B:$B,$B30,'2027 Calendar'!$D:$D,"Test") -> 0 | H30: None | I30: =IF(COUNTIFS('Covenant Tests'!$A:$A,$B30,'Covenant Tests'!$F:$F,">"&DATE(2027,12,31))=0,"",_xlfn.MINIFS('Covenant Tests'!$F:$F,'Covenant Tests'!$A:$A,$B30,'Covenant Tests'!$F:$F,">"&DATE(2027,12,31))) -> 47087
A31: 27 | B31: =HYPERLINK("#'Covenant Tests'!A"&(MATCH("Westfield 191st",'Covenant Tests'!$A$2:$A$107,0)+1),"Westfield 191st") -> Westfield 191st | C31: Fifth Third | D31: 47434 | E31: DSCR 1.00x, then 1.20x | F31: =IF(COUNTIFS('2027 Calendar'!$B:$B,$B31,'2027 Calendar'!$D:$D,"Test")=0,"None",_xlfn.MINIFS('2027 Calendar'!$A:$A,'2027 Calendar'!$B:$B,$B31,'2027 Calendar'!$D:$D,"Test")) -> None | G31: =COUNTIFS('2027 Calendar'!$B:$B,$B31,'2027 Calendar'!$D:$D,"Test") -> 0 | H31: None | I31: =IF(COUNTIFS('Covenant Tests'!$A:$A,$B31,'Covenant Tests'!$F:$F,">"&DATE(2027,12,31))=0,"",_xlfn.MINIFS('Covenant Tests'!$F:$F,'Covenant Tests'!$A:$A,$B31,'Covenant Tests'!$F:$F,">"&DATE(2027,12,31))) -> 47118
A32: 28 | B32: =HYPERLINK("#'Covenant Tests'!A"&(MATCH("Overland Park",'Covenant Tests'!$A$2:$A$107,0)+1),"Overland Park") -> Overland Park | C32: Simmons | D32: 47269 | E32: Cash trap until DSCR 1.25x; DSCR 1.25x and Debt Yield 10% to extend | F32: =IF(COUNTIFS('2027 Calendar'!$B:$B,$B32,'2027 Calendar'!$D:$D,"Test")=0,"None",_xlfn.MINIFS('2027 Calendar'!$A:$A,'2027 Calendar'!$B:$B,$B32,'2027 Calendar'!$D:$D,"Test")) -> None | G32: =COUNTIFS('2027 Calendar'!$B:$B,$B32,'2027 Calendar'!$D:$D,"Test") -> 0 | H32: Cash trap before stabilization (until stabilization); Loan to cost (At all times) | I32: =IF(COUNTIFS('Covenant Tests'!$A:$A,$B32,'Covenant Tests'!$F:$F,">"&DATE(2027,12,31))=0,"",_xlfn.MINIFS('Covenant Tests'!$F:$F,'Covenant Tests'!$A:$A,$B32,'Covenant Tests'!$F:$F,">"&DATE(2027,12,31))) -> 47269
